{"maps": [{"name": "Volskaya Industries", "teams": [{"name": "VAL", "score": "2", "progress": "0%", "fights": "9", "kills": "56"}, {"name": "SFS", "score": "2", "progress": "33%", "fights": "8", "kills": "41"}], "stats": [[{"name": "uNKOE", "kills": "8", "deathes": "7", "plusminus": "+1", "ultimates": "8", "firstbloods": "0", "rating": "1226", "id": "17"}, {"name": "Kariv", "kills": "17", "deathes": "8", "plusminus": "+9", "ultimates": "8", "firstbloods": "0", "rating": "1132", "id": "531"}, {"name": "Verbo", "kills": "1", "deathes": "2", "plusminus": "-1", "ultimates": "5", "firstbloods": "0", "rating": "1076", "id": "511"}, {"name": "Envy", "kills": "10", "deathes": "6", "plusminus": "+4", "ultimates": "0", "firstbloods": "0", "rating": "1020", "id": "999"}, {"name": "SoOn", "kills": "13", "deathes": "11", "plusminus": "+2", "ultimates": "9", "firstbloods": "+2", "rating": "995", "id": "152"}, {"name": "FaTe", "kills": "7", "deathes": "10", "plusminus": "-3", "ultimates": "4", "firstbloods": "-1", "rating": "995", "id": "990"}], [{"name": "Danteh", "kills": "13", "deathes": "5", "plusminus": "+8", "ultimates": "11", "firstbloods": "+1", "rating": "1179", "id": "710"}, {"name": "Sleepy", "kills": "3", "deathes": "6", "plusminus": "-3", "ultimates": "5", "firstbloods": "-1", "rating": "931", "id": "639"}, {"name": "Nevix", "kills": "7", "deathes": "10", "plusminus": "-3", "ultimates": "0", "firstbloods": "+1", "rating": "916", "id": "156"}, {"name": "dhaK", "kills": "2", "deathes": "9", "plusminus": "-7", "ultimates": "4", "firstbloods": "0", "rating": "903", "id": "307"}, {"name": "babybay", "kills": "10", "deathes": "13", "plusminus": "-3", "ultimates": "10", "firstbloods": "-1", "rating": "768", "id": "522"}, {"name": "nomy", "kills": "6", "deathes": "13", "plusminus": "-7", "ultimates": "5", "firstbloods": "-1", "rating": "667", "id": "299"}]]}, {"name": "Lijiang Tower", "teams": [{"name": "VAL", "score": "2", "progress": "0", "fights": "7", "kills": "31"}, {"name": "SFS", "score": "0", "progress": "0", "fights": "2", "kills": "15"}], "stats": [[{"name": "Envy", "kills": "7", "deathes": "1", "plusminus": "+6", "ultimates": "0", "firstbloods": "+3", "rating": "1396", "id": "999"}, {"name": "Verbo", "kills": "3", "deathes": "4", "plusminus": "-1", "ultimates": "2", "firstbloods": "+1", "rating": "1199", "id": "511"}, {"name": "FaTe", "kills": "6", "deathes": "2", "plusminus": "+4", "ultimates": "2", "firstbloods": "-1", "rating": "1120", "id": "990"}, {"name": "SoOn", "kills": "7", "deathes": "4", "plusminus": "+3", "ultimates": "4", "firstbloods": "+1", "rating": "1059", "id": "152"}, {"name": "uNKOE", "kills": "2", "deathes": "2", "plusminus": "0", "ultimates": "4", "firstbloods": "0", "rating": "NED?", "id": "17"}, {"name": "Kariv", "kills": "6", "deathes": "2", "plusminus": "+4", "ultimates": "4", "firstbloods": "-1", "rating": "NED?", "id": "531"}], [{"name": "Sleepy", "kills": "3", "deathes": "5", "plusminus": "-2", "ultimates": "2", "firstbloods": "-2", "rating": "965", "id": "639"}, {"name": "babybay", "kills": "7", "deathes": "7", "plusminus": "0", "ultimates": "3", "firstbloods": "+1", "rating": "904", "id": "522"}, {"name": "Danteh", "kills": "1", "deathes": "5", "plusminus": "-4", "ultimates": "3", "firstbloods": "+1", "rating": "863", "id": "710"}, {"name": "Nevix", "kills": "4", "deathes": "5", "plusminus": "-1", "ultimates": "0", "firstbloods": "0", "rating": "710", "id": "156"}, {"name": "nomy", "kills": "0", "deathes": "7", "plusminus": "-7", "ultimates": "2", "firstbloods": "-2", "rating": "675", "id": "299"}, {"name": "dhaK", "kills": "0", "deathes": "7", "plusminus": "-7", "ultimates": "3", "firstbloods": "-1", "rating": "671", "id": "307"}]]}, {"name": "King's Row", "teams": [{"name": "VAL", "score": "3", "progress": "81.9%", "fights": "11", "kills": "59"}, {"name": "SFS", "score": "3", "progress": "81.8%", "fights": "11", "kills": "53"}], "stats": [[{"name": "uNKOE", "kills": "7", "deathes": "7", "plusminus": "0", "ultimates": "12", "firstbloods": "-1", "rating": "1268", "id": "17"}, {"name": "Envy", "kills": "10", "deathes": "7", "plusminus": "+3", "ultimates": "2", "firstbloods": "+2", "rating": "1042", "id": "999"}, {"name": "Kariv", "kills": "17", "deathes": "9", "plusminus": "+8", "ultimates": "8", "firstbloods": "+1", "rating": "1040", "id": "531"}, {"name": "FaTe", "kills": "9", "deathes": "12", "plusminus": "-3", "ultimates": "6", "firstbloods": "-2", "rating": "988", "id": "990"}, {"name": "SoOn", "kills": "14", "deathes": "10", "plusminus": "+4", "ultimates": "7", "firstbloods": "+3", "rating": "854", "id": "152"}, {"name": "Verbo", "kills": "2", "deathes": "8", "plusminus": "-6", "ultimates": "4", "firstbloods": "-1", "rating": "811", "id": "511"}], [{"name": "Sleepy", "kills": "4", "deathes": "7", "plusminus": "-3", "ultimates": "7", "firstbloods": "+1", "rating": "1234", "id": "639"}, {"name": "nomy", "kills": "10", "deathes": "10", "plusminus": "0", "ultimates": "6", "firstbloods": "0", "rating": "1079", "id": "299"}, {"name": "dhaK", "kills": "4", "deathes": "8", "plusminus": "-4", "ultimates": "5", "firstbloods": "-3", "rating": "1067", "id": "307"}, {"name": "Danteh", "kills": "19", "deathes": "11", "plusminus": "+8", "ultimates": "9", "firstbloods": "-1", "rating": "1040", "id": "710"}, {"name": "babybay", "kills": "10", "deathes": "11", "plusminus": "-1", "ultimates": "10", "firstbloods": "+2", "rating": "889", "id": "522"}, {"name": "Nevix", "kills": "6", "deathes": "12", "plusminus": "-6", "ultimates": "5", "firstbloods": "-1", "rating": "714", "id": "156"}]]}, {"name": "Watchpoint: Gibraltar", "teams": [{"name": "VAL", "score": "4", "progress": "62.65", "fights": "10", "kills": "64"}, {"name": "SFS", "score": "4", "progress": "62.64", "fights": "9", "kills": "52"}], "stats": [[{"name": "Kariv", "kills": "22", "deathes": "9", "plusminus": "+13", "ultimates": "8", "firstbloods": "+3", "rating": "1347", "id": "531"}, {"name": "FaTe", "kills": "13", "deathes": "8", "plusminus": "+5", "ultimates": "9", "firstbloods": "+1", "rating": "1254", "id": "990"}, {"name": "Envy", "kills": "12", "deathes": "6", "plusminus": "+6", "ultimates": "0", "firstbloods": "-1", "rating": "1193", "id": "999"}, {"name": "Verbo", "kills": "1", "deathes": "8", "plusminus": "-7", "ultimates": "5", "firstbloods": "0", "rating": "1156", "id": "511"}, {"name": "SoOn", "kills": "11", "deathes": "8", "plusminus": "+3", "ultimates": "11", "firstbloods": "-1", "rating": "922", "id": "152"}, {"name": "uNKOE", "kills": "5", "deathes": "15", "plusminus": "-10", "ultimates": "5", "firstbloods": "-3", "rating": "806", "id": "17"}], [{"name": "babybay", "kills": "19", "deathes": "9", "plusminus": "+10", "ultimates": "9", "firstbloods": "+3", "rating": "1132", "id": "522"}, {"name": "dhaK", "kills": "0", "deathes": "11", "plusminus": "-11", "ultimates": "6", "firstbloods": "0", "rating": "1027", "id": "307"}, {"name": "Danteh", "kills": "16", "deathes": "11", "plusminus": "+5", "ultimates": "10", "firstbloods": "-3", "rating": "920", "id": "710"}, {"name": "Sleepy", "kills": "5", "deathes": "11", "plusminus": "-6", "ultimates": "5", "firstbloods": "+2", "rating": "863", "id": "639"}, {"name": "nomy", "kills": "7", "deathes": "12", "plusminus": "-5", "ultimates": "6", "firstbloods": "-3", "rating": "807", "id": "299"}, {"name": "Nevix", "kills": "5", "deathes": "10", "plusminus": "-5", "ultimates": "0", "firstbloods": "+2", "rating": "711", "id": "156"}]]}], "stats": [[{"name": "Envy", "kills": "39", "deathes": "20", "plusminus": "+19", "ultimates": "2", "firstbloods": "+4", "rating": "1200", "id": "999"}, {"name": "FaTe", "kills": "35", "deathes": "32", "plusminus": "+3", "ultimates": "21", "firstbloods": "-3", "rating": "1155", "id": "990"}, {"name": "Kariv", "kills": "62", "deathes": "28", "plusminus": "+34", "ultimates": "28", "firstbloods": "+3", "rating": "1130", "id": "531"}, {"name": "uNKOE", "kills": "22", "deathes": "31", "plusminus": "-9", "ultimates": "29", "firstbloods": "-4", "rating": "1126", "id": "17"}, {"name": "Verbo", "kills": "7", "deathes": "22", "plusminus": "-15", "ultimates": "16", "firstbloods": "0", "rating": "1077", "id": "511"}, {"name": "SoOn", "kills": "45", "deathes": "33", "plusminus": "+12", "ultimates": "31", "firstbloods": "+5", "rating": "941", "id": "152"}], [{"name": "Danteh", "kills": "49", "deathes": "32", "plusminus": "+17", "ultimates": "33", "firstbloods": "-2", "rating": "1008", "id": "710"}, {"name": "Sleepy", "kills": "15", "deathes": "29", "plusminus": "-14", "ultimates": "19", "firstbloods": "0", "rating": "1006", "id": "639"}, {"name": "babybay", "kills": "46", "deathes": "40", "plusminus": "+6", "ultimates": "32", "firstbloods": "+5", "rating": "902", "id": "522"}, {"name": "dhaK", "kills": "6", "deathes": "35", "plusminus": "-29", "ultimates": "18", "firstbloods": "-4", "rating": "893", "id": "307"}, {"name": "nomy", "kills": "23", "deathes": "42", "plusminus": "-19", "ultimates": "19", "firstbloods": "-6", "rating": "721", "id": "299"}, {"name": "Nevix", "kills": "22", "deathes": "37", "plusminus": "-15", "ultimates": "5", "firstbloods": "+2", "rating": "654", "id": "156"}]], "hero_stats": {"full_time": "1:52:26", "heros": [{"name": "D.Va", "time": "1:27:10", "percent": "77.53%"}, {"name": "Lucio", "time": "1:22:20", "percent": "73.23%"}, {"name": "Zenyatta", "time": "1:20:06", "percent": "71.24%"}, {"name": "Winston", "time": "1:18:36", "percent": "69.91%"}, {"name": "Tracer", "time": "1:10:25", "percent": "62.63%"}, {"name": "Soldier: 76", "time": "41:07", "percent": "36.57%"}, {"name": "Reinhardt", "time": "33:50", "percent": "30.09%"}, {"name": "Zarya", "time": "32:03", "percent": "28.51%"}, {"name": "Mercy", "time": "31:04", "percent": "27.63%"}, {"name": "Junkrat", "time": "29:38", "percent": "26.36%"}, {"name": "Widowmaker", "time": "26:25", "percent": "23.50%"}, {"name": "Mccree", "time": "22:51", "percent": "20.32%"}, {"name": "Sombra", "time": "16:10", "percent": "14.38%"}, {"name": "Ana", "time": "16:02", "percent": "14.26%"}, {"name": "Genji", "time": "10:24", "percent": "9.25%"}, {"name": "Moira", "time": "09:24", "percent": "8.36%"}, {"name": "Pharah", "time": "02:55", "percent": "2.59%"}, {"name": "Hanzo", "time": "02:11", "percent": "1.94%"}, {"name": "Doomfist", "time": "00:49", "percent": "0.73%"}, {"name": "Roadhog", "time": "00:43", "percent": "0.64%"}, {"name": "Mei", "time": "00:23", "percent": "0.34%"}, {"name": "Bastion", "time": "00:00", "percent": "0.00%"}, {"name": "Orisa", "time": "00:00", "percent": "0.00%"}, {"name": "Reaper", "time": "00:00", "percent": "0.00%"}, {"name": "Symmetra", "time": "00:00", "percent": "0.00%"}, {"name": "Torbj\u00f6rn", "time": "00:00", "percent": "0.00%"}], "compositions": [{"compositions": ["DPS (Offense/Defense)", "DPS (Offense/Defense)", "Support", "Support", "Tank", "Tank"], "time": "1:36:03", "percent": "85.43%"}, {"compositions": ["DPS (Offense/Defense)", "Support", "Support", "Tank", "Tank", "Tank"], "time": "09:10", "percent": "8.15%"}, {"compositions": ["DPS (Offense/Defense)", "DPS (Offense/Defense)", "DPS (Offense/Defense)", "Support", "Tank", "Tank"], "time": "05:33", "percent": "4.94%"}, {"compositions": ["DPS (Offense/Defense)", "DPS (Offense/Defense)", "DPS (Offense/Defense)", "Support", "Support", "Tank"], "time": "01:17", "percent": "1.14%"}, {"compositions": ["DPS (Offense/Defense)", "DPS (Offense/Defense)", "DPS (Offense/Defense)", "DPS (Offense/Defense)", "Support", "Tank"], "time": "00:23", "percent": "0.34%"}]}, "hero_stats_by_team": [], "teams": [{"name": "Los Angeles Valiant", "id": "333"}, {"name": "San Francisco Shock", "id": "338"}], "date": "21:00 - 28/02/2018"}