{"meta": {"strings": {"owl.rewards.info.description.logged-in": "\u60a8\u5df2\u767b\u5f55\uff0c\u6b22\u8fce\u9886\u53d6<a href=\"{0}\">\u89c2\u8d5b\u5956\u52b1</a>\u3002\u4ec5\u9002\u7528\u4e8e\u90e8\u5206\u5730\u533a\u3002", "owl.live-stream.results": "\u8d5b\u51b5", "owl.live-stream.phoenix-disclaimer": "\u6b22\u8fce\u524d\u5f80<a rel=\"external\" href=\"https://www.overwatchleague.cn\">overwatchleague.cn</a>\u89c2\u770b\u66f4\u9ad8\u753b\u8d28\u89c6\u9891\u3002", "owl.live-match.upcoming": "\u5373\u5c06\u76f4\u64ad", "owl.live-stream.game": "\u7b2c##\u5c40", "owl.live-match.now": "\u6b63\u5728\u76f4\u64ad", "owl.live-stream.view-more": "\u67e5\u770b\u66f4\u591a", "owl.live-stream.game-of": "\u6bd4\u8d5b\uff1a##/##", "owl.rewards.info.description": "<a href=\"{0}\">\u7acb\u5373\u767b\u5f55</a>\u4ee5\u9886\u53d6\u89c2\u8d5b\u5956\u52b1\u3002 <a href=\"{1}\">\u4ec5\u9002\u7528\u4e8e\u90e8\u5206\u5730\u533a </a>\u3002", "owl.live-stream.view-less": "\u6536\u8d77"}}, "data": {"nextMatch": {}, "liveMatch": {"clientHints": [], "liveStatus": "UPCOMING", "state": "PENDING", "startDate": "2018-04-11T23:00:00.000Z", "conclusionValue": 4, "scores": [{"value": 0}, {"value": 0}], "startDateTS": 1523487600000, "endDateTS": 1523494800000, "videos": [], "losses": [0, 0], "wins": [0, 0], "competitors": [{"id": 4408, "availableLanguages": ["en", "zh-tw", "es-mx", "ru", "ja", "th", "zh-cn", "es-es", "ko", "pt"], "type": "TEAM", "secondaryColor": "000000", "name": "\u4e0a\u6d77\u9f99\u4e4b\u961f", "logo": "https://bnetcmsus-a.akamaihd.net/cms/page_media/B0R64QSNCDLX1508792362793.png", "abbreviatedName": "SHD", "secondaryPhoto": "https://bnetcmsus-a.akamaihd.net/cms/template_resource/ZIVUVIWXNIFL1507822883114.svg", "addressCountry": "CN", "content": {"id": 4408, "description": "The dragon and the color red were chosen as themes in the team's logo because they resonate with Chinese culture and history.", "location": "Shanghai", "logoLockup": "https://dragons.overwatchleague.cn", "teamWebsite": "https://dragons.overwatchleague.cn", "name": "Dragons", "nid": 11, "icons": [{"usage": "main", "png": "https://bnetcmsus-a.akamaihd.net/cms/page_media/B0R64QSNCDLX1508792362793.png", "svg": "https://bnetcmsus-a.akamaihd.net/cms/template_resource/ZIVUVIWXNIFL1507822883114.svg"}, {"usage": "alt", "png": "https://bnetcmsus-a.akamaihd.net/cms/page_media/F7T6ISEVW0NN1512520986578.png", "svg": "https://bnetcmsus-a.akamaihd.net/cms/page_media/MHYBGBXKCBWW1512520986598.svg"}, {"usage": "mainName", "png": "https://bnetcmsus-a.akamaihd.net/cms/page_media/M703QHV3B6ZC1519747890887.svg", "svg": "https://bnetcmsus-a.akamaihd.net/cms/page_media/M703QHV3B6ZC1519747890887.svg"}], "abbreviatedName": "SHD", "colors": [{"usage": "primary", "name": "Shanghai Red", "color": {"color": "#D22630", "opacity": 1}}, {"usage": "secondary", "name": "Shanghai Black", "color": {"color": "#000000", "opacity": 1}}, {"usage": "tertiary", "name": "Shanghai Yellow", "color": {"color": "#FCE300", "opacity": 1}}]}, "homeLocation": "\u4e2d\u56fd\uff0c\u4e0a\u6d77", "icon": "https://bnetcmsus-a.akamaihd.net/cms/template_resource/ZIVUVIWXNIFL1507822883114.svg", "game": "OVERWATCH", "primaryColor": "d22630", "handle": "shanghai.1319"}, {"id": 4406, "availableLanguages": ["en", "zh-cn", "th", "ko", "ru", "ja", "zh-tw"], "type": "TEAM", "secondaryColor": "000000", "name": "\u6d1b\u6749\u77f6\u89d2\u6597\u58eb\u961f", "logo": "https://bnetcmsus-a.akamaihd.net/cms/page_media/3AEMOZZL76PF1508792362892.PNG", "abbreviatedName": "GLA", "secondaryPhoto": "https://bnetcmsus-a.akamaihd.net/cms/template_resource/CHTRRZCBEYGN1507822882862.svg", "addressCountry": "US", "content": {"id": 4406, "description": "The team is named for the fighters of ancient Rome, who were renowned for their ferocity and power; the roaring lion and battle-hardened shield also symbolize these qualities. The lion figure echoes the logo of the LA Rams, the pro football team owned by Gladiators owners Stan and Josh Kroenke. And the team colors, purple and white, reference the royal colors of the Roman emperors, to whom the gladiators dedicated their exploits.", "location": "Los Angeles", "logoLockup": "https://gladiators.overwatchleague.com", "teamWebsite": "https://gladiators.overwatchleague.com", "name": "Gladiators", "nid": 5, "icons": [{"usage": "main", "png": "https://bnetcmsus-a.akamaihd.net/cms/page_media/3AEMOZZL76PF1508792362892.PNG", "svg": "https://bnetcmsus-a.akamaihd.net/cms/template_resource/CHTRRZCBEYGN1507822882862.svg"}, {"usage": "alt", "png": "https://bnetcmsus-a.akamaihd.net/cms/page_media/01NO2I1B84CF1512520986350.png", "svg": "https://bnetcmsus-a.akamaihd.net/cms/page_media/HU1A12H9JPNS1512520986367.svg"}, {"usage": "mainName", "png": "https://bnetcmsus-a.akamaihd.net/cms/page_media/92RXGEWTP0B11519747890766.svg", "svg": "https://bnetcmsus-a.akamaihd.net/cms/page_media/92RXGEWTP0B11519747890766.svg"}], "abbreviatedName": "GLA", "colors": [{"usage": "primary", "name": "Gladiator Purple", "color": {"color": "#3C1053", "opacity": 1}}, {"usage": "secondary", "name": "Gladiator Black", "color": {"color": "#000000", "opacity": 1}}, {"usage": "tertiary", "name": "Gladiator White", "color": {"color": "#FFFFFF", "opacity": 1}}]}, "homeLocation": "\u52a0\u5229\u798f\u5c3c\u4e9a\u5dde\uff0c\u6d1b\u6749\u77f6", "icon": "https://bnetcmsus-a.akamaihd.net/cms/template_resource/CHTRRZCBEYGN1507822882862.svg", "game": "OVERWATCH", "primaryColor": "3c1053", "handle": "los-angeles-b.3827"}], "bracket": {"stage": {"id": 4669, "tournament": {"id": 3833, "title": "Overwatch League - Stage 3", "draft": false, "series": {"id": 55}, "featured": false, "game": "OVERWATCH", "availableLanguages": ["en"], "handle": "tournament-f8aaad2e-1d1b-ea4d-8fb6-53dda9f81d15"}, "availableLanguages": ["en"], "title": "Stage 3"}, "id": 2729, "winners": 4, "matchConclusionStrategy": "MINIMUM", "type": "OPEN_MATCH", "teamSize": 6, "repeatableMatchUps": 0, "advantageComparing": "AFTER_MATCH", "matchConclusionValue": 4, "thirdPlaceMatch": false, "allowDraw": false, "clientHints": []}, "dateCreated": 1507007342556, "id": 10345, "showStartTime": true, "flags": [], "timeToMatch": 26099840, "conclusionStrategy": "MINIMUM", "showEndTime": true, "youtubeId": "", "attributes": {}, "endDate": "2018-04-12T01:00:00.000Z", "ties": [0, 0], "games": [{"stats": null, "id": 8425, "attributesVersion": "0.2.0", "state": "PENDING", "attributes": {"mapGuid": "0x080000000000005B", "map": "temple-of-anubis"}, "number": 1}, {"stats": null, "id": 8426, "attributesVersion": "0.2.0", "state": "PENDING", "attributes": {"mapGuid": "0x080000000000075E", "map": "blizzard-world"}, "number": 2}, {"stats": null, "id": 8427, "attributesVersion": "0.2.0", "state": "PENDING", "attributes": {"mapGuid": "0x08000000000004B7", "map": "nepal"}, "number": 3}, {"stats": null, "id": 8429, "attributesVersion": "0.2.0", "state": "PENDING", "attributes": {"mapGuid": "0x08000000000005BB", "map": "route-66"}, "number": 4}], "handle": "match-3db8d580-1e45-9246-929b-81d88beff8a9"}}}