{"HeroRank_sombra_2": "5a9f3fbd17d009006904b5bb", "PlayerPickRate_4488": "5aac79b8ee920a00452a344d", "HeroRank_mercy_8": "5a9f3fbd17d009006904b592", "HeroRank_roadhog_33": "5a9f3fc217d009006904b6e6", "Match_10338": "5a95aafdfe88c20038b3ea1e", "HeroRank_soldier: 76_17": "5a9d66099f545467f5c6d8f6", "Match_10341": "5a95aafdfe88c20038b3ea21", "HeroRank_winston_1": "5a9f3fbd17d009006904b5b0", "HeroRank_pharah_11": "5a9f3fbb17d009006904b549", "HeroRank_reaper_10": "5a9f3fc017d009006904b62f", "CompositionUsage_ddssst_allmaps_all_maps": "5a9d30e09f54541bcd381c4a", "HeroRank_widowmaker_17": "5a9f3fc317d009006904b714", "Stage_2": "5a95aaf9fe88c20038b3e979", "PlayerPickRate_4621": "5aac79b9ee920a00452a3467", "Match_10545": "5a95aafefe88c20038b3ea59", "CompositionUsage_sstttt_maps_hollywood": "5a9d30e29f54541bcd381ce0", "Match_10261": "5a95aafcfe88c20038b3e9b7", "HeroRank_junkrat_1": "5a9f3fbf17d009006904b604", "HeroRank_lucio_17": "5a9f3fbd17d009006904b591", "Match_10566": "5a95aafcfe88c20038b3e9c4", "HeroRank_d.va_14": "5a9d66089f545467f5c6d8c4", "HeroRank_roadhog_34": "5a9f3fc117d009006904b6ad", "HeroRank_mercy_12": "5a9f3fbb17d009006904b543", "PlayerRank_97": "5a9f3fb9a22b9d00456ade6a", "HeroRank_moira_13": "5a9f3fbc17d009006904b564", "HeroRank_widowmaker_8": "5a9f3fc117d009006904b6a1", "CompositionUsage_sssttt_maptypes_control": "5a9d30e19f54541bcd381c6a", "PlayerRank_58": "5a9f3fb8a22b9d00456ade41", "CompositionUsage_dssttt_maps_eichenwalde": "5a9d30e29f54541bcd381cb5", "TeamHeroUsage_4523": "5a9d578dd50eee2ea31b70f8", "PlayerPickRate_4653": "5aac79b9ee920a00452a349d", "PlayerRank_8": "5a9f3fb8a22b9d00456ade0d", "HeroRank_zarya_23": "5a9f3fbf17d009006904b61a", "Match_10311": "5a95aafdfe88c20038b3e9f4", "Match_10259": "5a95aafcfe88c20038b3e9b5", "Stage_6": "5a95aafafe88c20038b3e97d", "CompositionUsage_ddsttt_maps_oasis": "5a9d30e29f54541bcd381ccc", "HeroRank_orisa_14": "5a9f3fc217d009006904b6d0", "Match_10360": "5a95aafefe88c20038b3ea35", "HeroRank_mccree_14": "5a9f3fbd17d009006904b5a6", "Match_10287": "5a95aafdfe88c20038b3e9da", "CompositionUsage_dssttt_maps_numbani": "5a9d30e19f54541bcd381c97", "HeroRank_pharah_9": "5a9f3fc317d009006904b703", "HeroRank_junkrat_15": "5a9f3fc317d009006904b701", "HeroRank_dva_12": "5a9f3fc117d009006904b6ac", "PlayerPickRate_4001": "5aac79b9ee920a00452a3469", "HeroRank_moira_3": "5a9f3fbd17d009006904b5b8", "Match_10485": "5a95aafffe88c20038b3ea84", "HeroRank_roadhog_8": "5a9f3fbc17d009006904b56c", "HeroRank_zenyatta_18": "5a9f3fc217d009006904b6f1", "HeroRank_moira_16": "5a9f3fc217d009006904b6ca", "CompositionUsage_dddsst_maps_route_66": "5a9d30e29f54541bcd381cb1", "PlayerPickRate_4144": "5aac79b9ee920a00452a345b", "HeroRank_zarya_4": "5a9f3fc017d009006904b657", "HeroRank_pharah_5": "5a9f3fc017d009006904b650", "CompositionUsage_dssttt_maps_horizon_lunar_colony": "5a9d30e29f54541bcd381cd1", "PlayerRank_91": "5a9f3fb9a22b9d00456ade63", "HeroRank_mccree_13": "5a9f3fbf17d009006904b626", "Match_10625": "5a95aafffe88c20038b3ea8e", "HeroRank_mccree_10": "5a9f3fbe17d009006904b5e4", "Match_10539": "5a95aafcfe88c20038b3e9cf", "Match_10472": "5a95aafefe88c20038b3ea77", "Match_10336": "5a95aafdfe88c20038b3ea1c", "HeroRank_junkrat_18": "5a9f3fc017d009006904b641", "HeroRank_zarya_26": "5a9f3fc117d009006904b699", "PlayerPickRate_4606": "5aac79b9ee920a00452a3491", "PlayerRank_75": "5a9f3fb9a22b9d00456ade52", "CompositionUsage_dddsst_maps_numbani": "5a9d30e19f54541bcd381c94", "Match_10583": "5a95aafdfe88c20038b3ea12", "HeroRank_pharah_21": "5a9f3fbf17d009006904b5fb", "HeroRank_reaper_4": "5a9f3fc117d009006904b68e", "HeroRank_moira_6": "5a9f3fbc17d009006904b55e", "HeroRank_widowmaker_10": "5a9f3fc117d009006904b698", "PlayerPickRate_4671": "5aac79baee920a00452a34b0", "TeamPickRate_NYE": "5aac79bb17d009688742069d", "HeroRank_d.va_12": "5a9d66089f545467f5c6d89d", "Match_10593": "5a95aafefe88c20038b3ea51", "CompositionUsage_dssttt_maps_hanamura": "5a9d30e29f54541bcd381ce8", "HeroRank_roadhog_5": "5a9f3fbf17d009006904b627", "CompositionUsage_dssttt_maps_volskaya_industries": "5a9d30e19f54541bcd381c9a", "HeroRank_ana_19": "5a9f3fbf17d009006904b600", "HeroRank_pharah_25": "5aac79b79f5454250d886c36", "CompositionUsage_dssttt_maps_route_66": "5a9d30e29f54541bcd381cb0", "CompositionUsage_dddstt_maptypes_hybrid": "5a9d30e19f54541bcd381c70", "Match_10367": "5a95aafefe88c20038b3ea3d", "PlayerRank_18": "5a9f3fb8a22b9d00456ade19", "Match_10286": "5a95aafcfe88c20038b3e9d9", "HeroRank_mccree_18": "5a9f3fc117d009006904b68d", "HeroRank_zarya_11": "5a9f3fbf17d009006904b622", "TeamHeroUsage_4406": "5a9d578cd50eee2ea31b70f6", "HeroRank_ana_15": "5a9f3fbd17d009006904b5b5", "Match_10241": "5a95aafcfe88c20038b3e9a3", "HeroRank_orisa_1": "5a9f3fc117d009006904b6a5", "HeroRank_junkrat_4": "5a9f3fc017d009006904b64e", "HeroRank_soldier: 76_15": "5a9d66069f545467f5c6d830", "CompositionUsage_dddsst_maps_oasis": "5a9d30e29f54541bcd381ccb", "HeroRank_junkrat_6": "5a9f3fbf17d009006904b5fa", "HeroRank_moira_1": "5a9f3fc017d009006904b64b", "CompositionUsage_dssttt_allmaps_all_maps": "5a9d30e09f54541bcd381c43", "PlayerRank_103": "5aac79659f5454303bab7414", "HeroRank_lucio_22": "5aa801b444d904006533ab78", "CompositionUsage_dddttt_allmaps_all_maps": "5a9d30e09f54541bcd381c4d", "Match_10478": "5a95aafefe88c20038b3ea7d", "HeroRank_reinhardt_15": "5a9f3fc317d009006904b721", "PlayerRank_17": "5a9f3fb8a22b9d00456ade18", "PlayerPickRate_4634": "5aac79b8ee920a00452a3451", "HeroRank_roadhog_39": "5aac79ae9f5454250d886bf7", "HeroRank_reinhardt_3": "5a9f3fbc17d009006904b56b", "CompositionUsage_sstttt_maps_oasis": "5a9d30e29f54541bcd381cc9", "HeroRank_orisa_12": "5a9f3fc217d009006904b6de", "PlayerRank_98": "5a9f3fb9a22b9d00456ade6b", "Match_10452": "5a95aafefe88c20038b3ea63", "HeroRank_zarya_12": "5a9f3fc117d009006904b6a4", "HeroRank_roadhog_25": "5a9f3fc317d009006904b71b", "Match_10269": "5a95aafcfe88c20038b3e9bf", "HeroRank_soldier-76_36": "5aac79ac9f5454250d886bee", "HeroRank_hanzo_8": "5a9f3fc017d009006904b659", "HeroRank_zenyatta_13": "5a9f3fbe17d009006904b5c7", "CompositionUsage_dddstt_maps_oasis": "5a9d30e29f54541bcd381cca", "CompositionUsage_ddsttt_maps_dorado": "5a9d30e19f54541bcd381c78", "HeroRank_hanzo_5": "5a9f3fc117d009006904b675", "HeroRank_tracer_18": "5a9f3fbf17d009006904b609", "Match_10307": "5a95aafdfe88c20038b3e9ef", "Stage_4": "5a95aafafe88c20038b3e97b", "HeroRank_roadhog_15": "5a9f3fc017d009006904b669", "HeroRank_mercy_23": "5a9f3fc217d009006904b6ee", "CompositionUsage_ddsttt_maps_hanamura": "5a9d30e39f54541bcd381ceb", "HeroRank_doomfist_3": "5a9f3fc117d009006904b6b7", "Match_10443": "5a95aafefe88c20038b3ea5a", "HeroRank_pharah_3": "5a9f3fbe17d009006904b5f2", "HeroRank_ana_14": "5a9f3fbf17d009006904b623", "CompositionUsage_sstttt_maptypes_escort": "5a9d30e09f54541bcd381c53", "Match_10223": "5a95aafcfe88c20038b3e991", "Match_10304": "5a95aafdfe88c20038b3e9ec", "HeroRank_pharah_8": "5a9f3fbd17d009006904b5a7", "HeroRank_mercy_15": "5a9f3fbf17d009006904b602", "HeroRank_tracer_31": "5aac79b49f5454250d886c21", "HeroRank_dva_21": "5a9f3fc317d009006904b71a", "TeamPickRate_SHD": "5aac79ba17d0096887420695", "Match_10580": "5a95aafdfe88c20038b3ea0f", "HeroRank_widowmaker_27": "5a9f3fc117d009006904b6ab", "HeroRank_dva_14": "5a9f3fc217d009006904b6d3", "Match_10246": "5a95aafcfe88c20038b3e9a8", "HeroRank_reinhardt_6": "5a9f3fbe17d009006904b5c9", "CompositionUsage_ddsstt_allmaps_all_maps": "5a9d30e09f54541bcd381c41", "PlayerPickRate_4079": "5aac79b9ee920a00452a348d", "Match_10320": "5a95aafdfe88c20038b3e9fd", "CompositionUsage_dddstt_maptypes_assault": "5a9d30e09f54541bcd381c59", "Competitor_4524": "5a95aaf4fe88c20038b3e968", "PlayerPickRate_4657": "5aac79b9ee920a00452a34a3", "HeroRank_roadhog_2": "5a9f3fbf17d009006904b5f3", "PlayerPickRate_4491": "5aac79b8ee920a00452a344a", "Match_10348": "5a95aafdfe88c20038b3ea29", "CompositionUsage_ddsttt_maps_horizon_lunar_colony": "5a9d30e29f54541bcd381cd5", "PlayerPickRate_4136": "5aac79b9ee920a00452a3483", "CompositionUsage_dddsst_maptypes_hybrid": "5a9d30e19f54541bcd381c72", "HeroRank_bastion_1": "5a9f3fbb17d009006904b52b", "CompositionUsage_ddddst_maps_dorado": "5a9d30e19f54541bcd381c7c", "HeroRank_reinhardt_8": "5a9f3fc117d009006904b6a6", "Match_10256": "5a95aafcfe88c20038b3e9b2", "PlayerRank_30": "5a9f3fb8a22b9d00456ade25", "HeroRank_pharah_12": "5a9f3fc217d009006904b6f9", "PlayerRank_48": "5a9f3fb8a22b9d00456ade37", "PlayerRank_90": "5a9f3fb9a22b9d00456ade62", "HeroRank_reaper_5": "5a9f3fc017d009006904b651", "PlayerPickRate_3660": "5aac79b9ee920a00452a346e", "Match_10565": "5a95aafcfe88c20038b3e9c3", "CompositionUsage_dddstt_maps_volskaya_industries": "5a9d30e19f54541bcd381c99", "HeroRank_winston_5": "5a9f3fbe17d009006904b5cc", "CompositionUsage_dssttt_maps_temple_of_anubis": "5a9d30e19f54541bcd381c7f", "HeroRank_zarya_20": "5a9f3fc017d009006904b65f", "TeamPickRate_DAL": "5aac79bb17d0096887420697", "CompositionUsage_ddsstt_maps_eichenwalde": "5a9d30e29f54541bcd381cb4", "HeroRank_soldier-76_29": "5a9f3fc317d009006904b712", "HeroRank_soldier-76_9": "5a9f3fc017d009006904b638", "TeamHeroUsage_4410": "5a9d578cd50eee2ea31b70ed", "PlayerPickRate_4625": "5aac79b9ee920a00452a348f", "HeroRank_widowmaker_2": "5a9f3fbe17d009006904b5d6", "CompositionUsage_ddsstt_maptypes_hybrid": "5a9d30e19f54541bcd381c6e", "Rank_4": "5a95aaf5ee920a788075a6ed", "Match_10351": "5a95aafdfe88c20038b3ea2c", "Rank_3": "5a95aaf5ee920a788075a6ec", "HeroRank_soldier: 76_22": "5a9d66039f545467f5c6d732", "HeroRank_mei_2": "5a9f3fc217d009006904b6f8", "Match_10476": "5a95aafefe88c20038b3ea7b", "HeroRank_mercy_19": "5a9f3fbd17d009006904b5b2", "Match_10270": "5a95aafcfe88c20038b3e9c1", "CompositionUsage_dddstt_maps_temple_of_anubis": "5a9d30e19f54541bcd381c7e", "HeroRank_junkrat_11": "5a9f3fc017d009006904b65a", "HeroRank_lucio_10": "5a9f3fbb17d009006904b537", "HeroRank_genji_6": "5a9f3fc017d009006904b658", "Match_10577": "5a95aafdfe88c20038b3ea0c", "HeroRank_reinhardt_11": "5a9f3fc317d009006904b70e", "CompositionUsage_dddstt_maptypes_escort": "5a9d30e09f54541bcd381c4f", "CompositionUsage_ddsttt_maps_lijiang_tower": "5a9d30e29f54541bcd381cdc", "HeroRank_roadhog_10": "5a9f3fc217d009006904b6d1", "CompositionUsage_ddsttt_allmaps_all_maps": "5a9d30e09f54541bcd381c44", "CompositionUsage_dssttt_maps_nepal": "5a9d30e19f54541bcd381ca0", "CompositionUsage_dddstt_maps_king's_row": "5a9d30e19f54541bcd381ca9", "HeroRank_genji_23": "5a9f3fc117d009006904b6b3", "Match_10455": "5a95aafefe88c20038b3ea66", "HeroRank_tracer_24": "5a9f3fc217d009006904b6c5", "Competitor_4523": "5a95aaf4fe88c20038b3e967", "Match_10314": "5a95aafdfe88c20038b3e9f7", "HeroRank_winston_17": "5a9f3fc317d009006904b71f", "HeroRank_dva_9": "5a9f3fbf17d009006904b5ff", "HeroRank_tracer_13": "5a9f3fc117d009006904b697", "HeroRank_roadhog_41": "5aac79b59f5454250d886c29", "HeroRank_lucio_21": "5a9f3fc117d009006904b686", "HeroRank_genji_7": "5a9f3fbf17d009006904b5f9", "Match_10295": "5a95aafdfe88c20038b3e9e2", "Match_10239": "5a95aafcfe88c20038b3e9a1", "HeroRank_d.va_7": "5a9d66079f545467f5c6d855", "PlayerPickRate_4619": "5aac79b9ee920a00452a3464", "HeroRank_soldier-76_10": "5a9f3fc117d009006904b6b5", "HeroRank_dva_16": "5a9f3fc117d009006904b6a3", "HeroRank_bastion_2": "5a9f3fbf17d009006904b60c", "CompositionUsage_ddssst_maps_volskaya_industries": "5a9d30e19f54541bcd381c9e", "PlayerPickRate_3577": "5aac79b9ee920a00452a3470", "CompositionUsage_sssttt_allmaps_all_maps": "5a9d30e09f54541bcd381c4b", "PlayerRank_57": "5a9f3fb8a22b9d00456ade40", "PlayerPickRate_4620": "5aac79b9ee920a00452a3489", "PlayerPickRate_4636": "5aac79b8ee920a00452a3450", "Match_10567": "5a95aafcfe88c20038b3e9c5", "PlayerRank_40": "5a9f3fb8a22b9d00456ade2f", "Match_10339": "5a95aafdfe88c20038b3ea1f", "Competitor_4403": "5a95aaf4fe88c20038b3e96b", "HeroRank_roadhog_9": "5a9f3fc217d009006904b6bb", "HeroRank_sombra_14": "5a9f3fc217d009006904b6e8", "HeroRank_soldier: 76_14": "5a9d66049f545467f5c6d785", "PlayerPickRate_4610": "5aac79b9ee920a00452a3494", "HeroRank_soldier-76_14": "5a9f3fbd17d009006904b5a8", "HeroRank_doomfist_2": "5a9f3fbe17d009006904b5ed", "HeroRank_reinhardt_5": "5a9f3fbd17d009006904b58e", "CompositionUsage_ddddtt_maps_junkertown": "5a9d30e29f54541bcd381cc6", "HeroRank_roadhog_13": "5a9f3fc117d009006904b683", "PlayerRank_31": "5a9f3fb8a22b9d00456ade26", "CompositionUsage_dstttt_maps_horizon_lunar_colony": "5a9d30e29f54541bcd381cd3", "Match_10333": "5a95aafdfe88c20038b3ea19", "HeroRank_mccree_8": "5a9f3fc017d009006904b642", "PlayerPickRate_4614": "5aac79b9ee920a00452a3463", "CompositionUsage_dssstt_maps_king's_row": "5a9d30e29f54541bcd381cac", "Match_10288": "5a95aafdfe88c20038b3e9db", "HeroRank_soldier-76_30": "5a9f3fbe17d009006904b5e8", "Match_10300": "5a95aafdfe88c20038b3e9e8", "Match_10229": "5a95aafcfe88c20038b3e997", "Match_10281": "5a95aafcfe88c20038b3e9d4", "Match_10582": "5a95aafdfe88c20038b3ea11", "Match_10576": "5a95aafdfe88c20038b3ea0b", "HeroRank_mccree_11": "5a9f3fbf17d009006904b605", "Match_10292": "5a95aafdfe88c20038b3e9df", "PlayerPickRate_4631": "5aac79b9ee920a00452a345a", "HeroRank_moira_14": "5a9f3fbc17d009006904b586", "PlayerRank_59": "5a9f3fb8a22b9d00456ade42", "HeroRank_zarya_24": "5a9f3fc017d009006904b66b", "Match_10306": "5a95aafdfe88c20038b3e9ee", "PlayerRank_44": "5a9f3fb8a22b9d00456ade33", "HeroRank_zarya_7": "5a9f3fc017d009006904b648", "PlayerPickRate_4635": "5aac79b8ee920a00452a344c", "HeroRank_mercy_22": "5a9f3fbf17d009006904b625", "Match_10587": "5a95aafdfe88c20038b3ea16", "CompositionUsage_dddsst_maps_eichenwalde": "5a9d30e29f54541bcd381cb7", "CompositionUsage_ddsstt_maps_route_66": "5a9d30e29f54541bcd381cad", "Match_10302": "5a95aafdfe88c20038b3e9ea", "CompositionUsage_ddssst_maps_hollywood": "5a9d30e29f54541bcd381ce5", "HeroRank_soldier: 76_18": "5a9d66059f545467f5c6d7df", "HeroRank_roadhog_29": "5a9f3fc117d009006904b696", "HeroRank_tracer_29": "5aa801b744d904006533aba0", "HeroRank_winston_3": "5a9f3fbc17d009006904b56d", "CompositionUsage_dssstt_maps_ilios": "5a9d30e19f54541bcd381c90", "HeroRank_genji_13": "5a9f3fc117d009006904b67a", "HeroRank_d.va_16": "5a9d66089f545467f5c6d893", "PlayerRank_87": "5a9f3fb9a22b9d00456ade5e", "PlayerRank_78": "5a9f3fb9a22b9d00456ade55", "PlayerPickRate_4656": "5aac79b9ee920a00452a3476", "PlayerPickRate_4093": "5aac79b9ee920a00452a3496", "TeamHeroUsage_4524": "5a9d578cd50eee2ea31b70f1", "CompositionUsage_dddsst_maptypes_assault": "5a9d30e09f54541bcd381c5c", "HeroRank_zenyatta_8": "5a9f3fc117d009006904b6b2", "HeroRank_genji_22": "5a9f3fbd17d009006904b59a", "PlayerPickRate_4094": "5aac79b9ee920a00452a3490", "HeroRank_zarya_8": "5a9f3fc117d009006904b6a2", "HeroRank_junkrat_21": "5aa1953344d9040044fa662d", "HeroRank_mercy_1": "5a9f3fbc17d009006904b563", "HeroRank_sombra_10": "5a9f3fc017d009006904b663", "HeroRank_roadhog_36": "5a9f3fbc17d009006904b552", "Match_10265": "5a95aafcfe88c20038b3e9bb", "HeroRank_roadhog_20": "5a9f3fc017d009006904b652", "Match_10591": "5a95aafefe88c20038b3ea4f", "Match_10262": "5a95aafcfe88c20038b3e9b8", "Match_10279": "5a95aafcfe88c20038b3e9d2", "PlayerPickRate_4648": "5aac79b9ee920a00452a349e", "Match_10363": "5a95aafefe88c20038b3ea39", "HeroRank_soldier: 76_2": "5a9d66039f545467f5c6d761", "Competitor_4407": "5a95aaf5fe88c20038b3e96f", "Match_10296": "5a95aafdfe88c20038b3e9e4", "HeroRank_mercy_18": "5a9f3fbd17d009006904b59e", "Match_10626": "5a95aafffe88c20038b3ea8f", "HeroRank_mccree_12": "5a9f3fbe17d009006904b5d0", "Match_10230": "5a95aafcfe88c20038b3e998", "HeroRank_soldier: 76_25": "5a9d66099f545467f5c6d8d8", "PlayerRank_23": "5a9f3fb8a22b9d00456ade1e", "CompositionUsage_ddssst_maptypes_assault": "5a9d30e09f54541bcd381c61", "HeroRank_mei_3": "5aa801b744d904006533aba1", "HeroRank_widowmaker_11": "5a9f3fc017d009006904b647", "Rank_9": "5a95aaf5ee920a788075a6f2", "HeroRank_winston_9": "5a9f3fc217d009006904b6c8", "HeroRank_ana_21": "5a9f3fc217d009006904b6ec", "HeroRank_soldier-76_11": "5a9f3fbc17d009006904b578", "PlayerRank_74": "5a9f3fb9a22b9d00456ade51", "HeroRank_mercy_24": "5a9f3fbf17d009006904b614", "PlayerRank_21": "5a9f3fb8a22b9d00456ade1c", "HeroRank_reinhardt_12": "5a9f3fc317d009006904b70b", "Match_10581": "5a95aafdfe88c20038b3ea10", "CompositionUsage_ddssst_maps_oasis": "5a9d30e29f54541bcd381ccd", "PlayerPickRate_4099": "5aac79b9ee920a00452a3493", "HeroRank_hanzo_1": "5a9f3fbe17d009006904b5ef", "PlayerRank_38": "5a9f3fb8a22b9d00456ade2d", "HeroRank_mercy_9": "5a9f3fbd17d009006904b5b4", "Match_10254": "5a95aafcfe88c20038b3e9b0", "Match_10347": "5a95aafdfe88c20038b3ea28", "Match_10318": "5a95aafdfe88c20038b3e9fb", "PlayerPickRate_4658": "5aac79b9ee920a00452a34a2", "CompositionUsage_dddsst_maps_ilios": "5a9d30e19f54541bcd381c8a", "Match_10278": "5a95aafcfe88c20038b3e9d0", "HeroRank_ana_13": "5a9f3fbd17d009006904b5c0", "Match_10462": "5a95aafefe88c20038b3ea6d", "HeroRank_sombra_3": "5a9f3fc117d009006904b6a0", "CompositionUsage_ddsttt_maps_nepal": "5a9d30e19f54541bcd381ca2", "Match_10631": "5a95aafffe88c20038b3ea94", "HeroRank_roadhog_21": "5a9f3fbb17d009006904b53e", "PlayerRank_42": "5a9f3fb8a22b9d00456ade31", "CompositionUsage_sstttt_maptypes_control": "5a9d30e09f54541bcd381c64", "HeroRank_zarya_16": "5a9f3fc317d009006904b71c", "HeroRank_dva_13": "5a9f3fc117d009006904b682", "Match_10250": "5a95aafcfe88c20038b3e9ac", "Match_10322": "5a95aafdfe88c20038b3ea02", "PlayerPickRate_4662": "5aac79b9ee920a00452a347f", "CompositionUsage_dssttt_maptypes_hybrid": "5a9d30e19f54541bcd381c6f", "CompositionUsage_dddsst_maps_watchpoint:_gibraltar": "5a9d30e39f54541bcd381cf1", "HeroRank_soldier-76_21": "5a9f3fc017d009006904b653", "HeroRank_d.va_6": "5a9d66039f545467f5c6d750", "HeroRank_roadhog_19": "5a9f3fbd17d009006904b5b9", "Match_10249": "5a95aafcfe88c20038b3e9ab", "HeroRank_ana_3": "5a9f3fbc17d009006904b55b", "HeroRank_mercy_2": "5a9f3fbb17d009006904b533", "HeroRank_junkrat_3": "5a9f3fbe17d009006904b5cf", "HeroRank_roadhog_26": "5a9f3fc217d009006904b6c3", "HeroRank_genji_24": "5a9f3fc117d009006904b69a", "HeroRank_ana_27": "5aac79b19f5454250d886c15", "HeroRank_mccree_24": "5a9f3fc117d009006904b69c", "PlayerRank_51": "5a9f3fb8a22b9d00456ade3a", "Match_10252": "5a95aafcfe88c20038b3e9ae", "HeroRank_sombra_5": "5a9f3fbb17d009006904b540", "PlayerRank_28": "5a9f3fb8a22b9d00456ade23", "HeroRank_mercy_16": "5a9f3fc017d009006904b64a", "PlayerPickRate_4654": "5aac79b9ee920a00452a3495", "HeroRank_reaper_6": "5a9f3fc017d009006904b637", "Match_10590": "5a95aafefe88c20038b3ea4e", "HeroRank_reinhardt_9": "5a9f3fc217d009006904b6c7", "HeroRank_widowmaker_16": "5a9f3fbf17d009006904b62a", "HeroRank_reinhardt_13": "5a9f3fbc17d009006904b57c", "HeroRank_ana_4": "5a9f3fbd17d009006904b5aa", "HeroRank_widowmaker_21": "5a9f3fc317d009006904b709", "CompositionUsage_dssstt_maps_hanamura": "5a9d30e39f54541bcd381ced", "Match_10482": "5a95aafefe88c20038b3ea81", "Match_10253": "5a95aafcfe88c20038b3e9af", "HeroRank_reinhardt_10": "5a9f3fc017d009006904b666", "CompositionUsage_dddsst_maps_lijiang_tower": "5a9d30e29f54541bcd381cd9", "HeroRank_moira_7": "5a9f3fbd17d009006904b594", "Match_10315": "5a95aafdfe88c20038b3e9f8", "HeroRank_tracer_11": "5a9f3fc117d009006904b6b6", "PlayerPickRate_3985": "5aac79b9ee920a00452a34a1", "HeroRank_d.va_18": "5a9d66099f545467f5c6d8ce", "HeroRank_pharah_17": "5a9f3fc117d009006904b69d", "Match_10268": "5a95aafcfe88c20038b3e9be", "HeroRank_soldier: 76_28": "5a9d66099f545467f5c6d8c8", "CompositionUsage_dssstt_maptypes_hybrid": "5a9d30e19f54541bcd381c74", "Match_10596": "5a95aafefe88c20038b3ea54", "Match_10458": "5a95aafefe88c20038b3ea69", "Match_10588": "5a95aafefe88c20038b3ea4c", "Match_10463": "5a95aafefe88c20038b3ea6e", "PlayerRank_7": "5a9f3fb8a22b9d00456ade0c", "HeroRank_pharah_7": "5a9f3fbc17d009006904b580", "PlayerPickRate_4665": "5aac79b9ee920a00452a34a4", "CompositionUsage_ddsttt_maps_eichenwalde": "5a9d30e29f54541bcd381cb8", "HeroRank_zarya_27": "5aa1953744d9040044fa6635", "HeroRank_d.va_11": "5a9d66069f545467f5c6d802", "Match_10630": "5a95aafffe88c20038b3ea93", "HeroRank_moira_4": "5a9f3fbb17d009006904b52d", "PlayerPickRate_4642": "5aac79b9ee920a00452a346f", "Match_10546": "5a95aafffe88c20038b3ea96", "HeroRank_moira_8": "5a9f3fbf17d009006904b615", "Match_10352": "5a95aafdfe88c20038b3ea2d", "Match_10372": "5a95aafefe88c20038b3ea43", "HeroRank_mccree_19": "5a9f3fbf17d009006904b61d", "HeroRank_dva_19": "5a9f3fc217d009006904b6cf", "Match_10373": "5a95aafefe88c20038b3ea44", "HeroRank_genji_2": "5a9f3fbc17d009006904b551", "HeroRank_mccree_3": "5a9f3fbd17d009006904b59d", "HeroRank_ana_2": "5a9f3fbb17d009006904b52a", "TeamPickRate_SEO": "5aac79ba17d0096887420694", "PlayerRank_82": "5a9f3fb9a22b9d00456ade59", "HeroRank_doomfist_1": "5a9f3fbe17d009006904b5cd", "CompositionUsage_ddssst_maps_route_66": "5a9d30e29f54541bcd381cb3", "HeroRank_soldier-76_23": "5a9f3fbf17d009006904b5fd", "HeroRank_pharah_19": "5a9f3fc217d009006904b6e4", "CompositionUsage_dssstt_maps_temple_of_anubis": "5a9d30e19f54541bcd381c83", "HeroRank_zarya_5": "5a9f3fbc17d009006904b550", "HeroRank_pharah_15": "5a9f3fc017d009006904b65b", "CompositionUsage_ddssst_maps_nepal": "5a9d30e19f54541bcd381ca4", "HeroRank_soldier: 76_8": "5a9d66079f545467f5c6d865", "HeroRank_mercy_26": "5a9f3fbd17d009006904b5ac", "HeroRank_tracer_9": "5a9f3fbf17d009006904b5fe", "HeroRank_d.va_3": "5a9d66039f545467f5c6d740", "CompositionUsage_dddttt_maptypes_control": "5a9d30e19f54541bcd381c6d", "CompositionUsage_ddssst_maps_hanamura": "5a9d30e39f54541bcd381cec", "PlayerRank_61": "5a9f3fb8a22b9d00456ade44", "PlayerRank_67": "5a9f3fb9a22b9d00456ade4a", "CompositionUsage_ddsstt_maps_lijiang_tower": "5a9d30e29f54541bcd381cd6", "TeamPickRate_BOS": "5aac79bb17d009688742069c", "CompositionUsage_ddsstt_maps_nepal": "5a9d30e19f54541bcd381c9f", "HeroRank_genji_4": "5a9f3fc117d009006904b674", "HeroRank_lucio_16": "5a9f3fbf17d009006904b5f7", "CompositionUsage_dssttt_maps_dorado": "5a9d30e19f54541bcd381c79", "Match_10365": "5a95aafefe88c20038b3ea3b", "TeamPickRate_VAL": "5aac79ba17d0096887420692", "HeroRank_mccree_2": "5a9f3fbe17d009006904b5de", "HeroRank_dva_7": "5a9f3fc017d009006904b668", "PlayerPickRate_4489": "5aac79b8ee920a00452a344f", "HeroRank_soldier: 76_20": "5a9d66049f545467f5c6d774", "Match_10569": "5a95aafcfe88c20038b3e9c7", "CompositionUsage_ddsttt_maptypes_hybrid": "5a9d30e19f54541bcd381c73", "HeroRank_tracer_16": "5a9f3fc017d009006904b639", "PlayerPickRate_4616": "5aac79b9ee920a00452a3472", "Match_10237": "5a95aafcfe88c20038b3e99f", "HeroRank_soldier: 76_27": "5a9d66069f545467f5c6d800", "CompositionUsage_ddddst_maptypes_control": "5a9d30e19f54541bcd381c6c", "HeroRank_dva_10": "5a9f3fbf17d009006904b618", "HeroRank_widowmaker_15": "5a9f3fbe17d009006904b5e2", "PlayerRank_64": "5a9f3fb8a22b9d00456ade47", "HeroRank_roadhog_28": "5a9f3fbf17d009006904b619", "HeroRank_soldier-76_34": "5aa801b744d904006533ab9e", "HeroRank_bastion_5": "5a9f3fbb17d009006904b542", "Match_10592": "5a95aafefe88c20038b3ea50", "HeroRank_junkrat_2": "5a9f3fbb17d009006904b548", "HeroRank_mercy_13": "5a9f3fbe17d009006904b5d8", "HeroRank_soldier: 76_11": "5a9d66039f545467f5c6d758", "Match_10312": "5a95aafdfe88c20038b3e9f5", "HeroRank_dva_1": "5a9f3fbb17d009006904b53c", "PlayerPickRate_4645": "5aac79b9ee920a00452a3460", "PlayerRank_88": "5a9f3fb9a22b9d00456ade5f", "HeroRank_roadhog_16": "5a9f3fc017d009006904b65c", "PlayerPickRate_4142": "5aac79b8ee920a00452a3445", "Match_10371": "5a95aafefe88c20038b3ea42", "Match_10343": "5a95aafdfe88c20038b3ea23", "Match_10464": "5a95aafefe88c20038b3ea6f", "HeroRank_soldier-76_31": "5a9f3fc317d009006904b706", "HeroRank_tracer_15": "5a9f3fc117d009006904b672", "PlayerRank_63": "5a9f3fb8a22b9d00456ade46", "HeroRank_junkrat_7": "5a9f3fc217d009006904b6c1", "HeroRank_tracer_2": "5a9f3fc117d009006904b680", "PlayerPickRate_4649": "5aac79b9ee920a00452a3492", "HeroRank_tracer_27": "5a9f3fc217d009006904b6e9", "Match_10471": "5a95aafefe88c20038b3ea76", "Match_10466": "5a95aafefe88c20038b3ea71", "Match_10533": "5a95aafbfe88c20038b3e98d", "HeroRank_soldier: 76_31": "5a9d660a9f545467f5c6d903", "HeroRank_sombra_20": "5a9f3fbc17d009006904b559", "HeroRank_hanzo_7": "5a9f3fbf17d009006904b62c", "HeroRank_winston_2": "5a9f3fbc17d009006904b57d", "HeroRank_ana_5": "5a9f3fbd17d009006904b5bd", "HeroRank_widowmaker_22": "5a9f3fbf17d009006904b621", "HeroRank_genji_9": "5a9f3fbb17d009006904b547", "HeroRank_lucio_9": "5a9f3fbd17d009006904b5ab", "HeroRank_ana_10": "5a9f3fbf17d009006904b60b", "HeroRank_zenyatta_4": "5a9f3fbb17d009006904b546", "HeroRank_sombra_11": "5a9f3fc117d009006904b67f", "CompositionUsage_dstttt_maptypes_assault": "5a9d30e09f54541bcd381c5e", "TeamHeroUsage_4404": "5a9d578cd50eee2ea31b70f7", "CompositionUsage_dddsst_maps_nepal": "5a9d30e19f54541bcd381ca1", "HeroRank_sombra_13": "5a9f3fc017d009006904b65d", "HeroRank_soldier: 76_1": "5a9d66089f545467f5c6d887", "PlayerPickRate_4607": "5aac79b9ee920a00452a34a0", "HeroRank_orisa_10": "5a9f3fbd17d009006904b5ad", "Match_10543": "5a95aafefe88c20038b3ea58", "PlayerRank_4": "5a9f3fb8a22b9d00456ade09", "HeroRank_ana_25": "5aa1953444d9040044fa6631", "Match_10531": "5a95aafbfe88c20038b3e98b", "PlayerPickRate_4492": "5aac79b8ee920a00452a3448", "CompositionUsage_ddddst_allmaps_all_maps": "5a9d30e09f54541bcd381c47", "PlayerPickRate_4661": "5aac79baee920a00452a34af", "PlayerRank_104": "5aac79659f5454303bab7415", "HeroRank_mercy_6": "5a9f3fbd17d009006904b5c5", "PlayerRank_66": "5a9f3fb9a22b9d00456ade49", "Match_10228": "5a95aafcfe88c20038b3e996", "CompositionUsage_dddstt_maps_hanamura": "5a9d30e29f54541bcd381ce9", "CompositionUsage_dssstt_maps_numbani": "5a9d30e19f54541bcd381c96", "HeroRank_lucio_18": "5a9f3fbc17d009006904b55d", "HeroRank_zenyatta_21": "5a9f3fc217d009006904b6bd", "PlayerPickRate_4668": "5aac79b9ee920a00452a348b", "CompositionUsage_ddddst_maptypes_hybrid": "5a9d30e19f54541bcd381c75", "Competitor_4410": "5a95aaf5fe88c20038b3e972", "HeroRank_tracer_21": "5a9f3fc317d009006904b713", "Match_10340": "5a95aafdfe88c20038b3ea20", "HeroRank_orisa_8": "5a9f3fc217d009006904b6e0", "HeroRank_mccree_22": "5a9f3fc017d009006904b636", "Match_10585": "5a95aafdfe88c20038b3ea14", "HeroRank_mercy_5": "5a9f3fbc17d009006904b556", "HeroRank_ana_7": "5a9f3fbc17d009006904b583", "CompositionUsage_dddstt_maptypes_control": "5a9d30e19f54541bcd381c65", "Match_10528": "5a95aafbfe88c20038b3e988", "HeroRank_reinhardt_4": "5a9f3fc217d009006904b6e1", "PlayerPickRate_4358": "5aac79baee920a00452a34b1", "PlayerRank_43": "5a9f3fb8a22b9d00456ade32", "HeroRank_zarya_9": "5a9f3fbb17d009006904b53f", "CompositionUsage_ddssst_maps_watchpoint:_gibraltar": "5a9d30e39f54541bcd381cf2", "Match_10530": "5a95aafbfe88c20038b3e98a", "Match_10527": "5a95aafbfe88c20038b3e987", "Match_10456": "5a95aafefe88c20038b3ea67", "CompositionUsage_ddddst_maptypes_escort": "5a9d30e09f54541bcd381c55", "Match_10225": "5a95aafcfe88c20038b3e993", "TeamHeroUsage_4408": "5a9d578dd50eee2ea31b70f9", "Rank_1": "5a95aaf5ee920a788075a6ea", "Match_10248": "5a95aafcfe88c20038b3e9aa", "HeroRank_widowmaker_24": "5a9f3fbf17d009006904b5f5", "PlayerPickRate_4128": "5aac79b9ee920a00452a347a", "HeroRank_orisa_7": "5a9f3fbc17d009006904b589", "PlayerRank_2": "5a9f3fb8a22b9d00456ade07", "PlayerRank_39": "5a9f3fb8a22b9d00456ade2e", "HeroRank_dva_18": "5a9f3fc217d009006904b6dd", "TeamHeroUsage_4409": "5a9d578cd50eee2ea31b70f5", "HeroRank_bastion_4": "5a9f3fbd17d009006904b5b6", "PlayerRank_83": "5a9f3fb9a22b9d00456ade5a", "Match_10369": "5a95aafefe88c20038b3ea40", "HeroRank_mccree_20": "5a9f3fc217d009006904b6d4", "CompositionUsage_ddsstt_maps_watchpoint:_gibraltar": "5a9d30e39f54541bcd381cee", "CompositionUsage_ddddst_maps_temple_of_anubis": "5a9d30e19f54541bcd381c85", "CompositionUsage_ddddst_maps_junkertown": "5a9d30e29f54541bcd381cc5", "PlayerRank_96": "5a9f3fb9a22b9d00456ade69", "PlayerPickRate_4660": "5aac79b9ee920a00452a347c", "HeroRank_d.va_2": "5a9d66039f545467f5c6d72d", "HeroRank_lucio_5": "5a9f3fbd17d009006904b5c1", "CompositionUsage_ddddst_maps_volskaya_industries": "5a9d30e19f54541bcd381c9c", "HeroRank_soldier: 76_24": "5a9d66059f545467f5c6d7cb", "PlayerPickRate_4024": "5aac79b9ee920a00452a3487", "Match_10529": "5a95aafbfe88c20038b3e989", "PlayerRank_86": "5a9f3fb9a22b9d00456ade5d", "CompositionUsage_ddsstt_maps_junkertown": "5a9d30e29f54541bcd381cbe", "HeroRank_reinhardt_2": "5a9f3fbd17d009006904b5ae", "TeamPickRate_FLA": "5aac79bb17d0096887420699", "Match_10257": "5a95aafcfe88c20038b3e9b3", "Match_10243": "5a95aafcfe88c20038b3e9a5", "HeroRank_sombra_15": "5a9f3fbf17d009006904b616", "Match_10448": "5a95aafefe88c20038b3ea5f", "HeroRank_junkrat_10": "5a9f3fbe17d009006904b5e3", "HeroRank_tracer_6": "5a9f3fbe17d009006904b5d5", "Match_10454": "5a95aafefe88c20038b3ea65", "HeroRank_roadhog_4": "5a9f3fc017d009006904b671", "HeroRank_genji_21": "5a9f3fbf17d009006904b62b", "HeroRank_roadhog_38": "5aa801b644d904006533ab83", "CompositionUsage_sstttt_allmaps_all_maps": "5a9d30e09f54541bcd381c45", "PlayerPickRate_3380": "5aac79b9ee920a00452a346c", "Stage_7": "5a95aafafe88c20038b3e97e", "HeroRank_widowmaker_20": "5a9f3fc217d009006904b6f0", "Match_10344": "5a95aafdfe88c20038b3ea24", "CompositionUsage_ddddst_maps_eichenwalde": "5a9d30e29f54541bcd381cbb", "HeroRank_widowmaker_23": "5a9f3fc217d009006904b6ea", "Match_10542": "5a95aafdfe88c20038b3ea18", "HeroRank_dva_4": "5a9f3fbc17d009006904b567", "HeroRank_tracer_17": "5a9f3fc117d009006904b6aa", "HeroRank_roadhog_37": "5aa801b744d904006533ab9f", "PlayerRank_71": "5a9f3fb9a22b9d00456ade4e", "Match_10578": "5a95aafdfe88c20038b3ea0d", "CompositionUsage_dssttt_maptypes_control": "5a9d30e09f54541bcd381c63", "Stage_3": "5a95aaf9fe88c20038b3e97a", "HeroRank_sombra_7": "5a9f3fbe17d009006904b5e9", "Match_10282": "5a95aafcfe88c20038b3e9d5", "Match_10357": "5a95aafefe88c20038b3ea32", "HeroRank_orisa_9": "5a9f3fc317d009006904b70a", "HeroRank_winston_19": "5a9f3fc317d009006904b718", "Match_10457": "5a95aafefe88c20038b3ea68", "Match_10595": "5a95aafefe88c20038b3ea53", "HeroRank_dva_15": "5a9f3fbc17d009006904b588", "HeroRank_orisa_3": "5a9f3fc217d009006904b6d9", "HeroRank_genji_20": "5a9f3fc217d009006904b6f5", "PlayerPickRate_4659": "5aac79b9ee920a00452a347d", "Match_10537": "5a95aafcfe88c20038b3e9ce", "HeroRank_soldier: 76_23": "5a9d66059f545467f5c6d7ec", "PlayerPickRate_4638": "5aac79baee920a00452a34ab", "PlayerRank_95": "5a9f3fb9a22b9d00456ade68", "Match_10599": "5a95aafefe88c20038b3ea57", "Match_10308": "5a95aafdfe88c20038b3e9f0", "Competitor_4404": "5a95aaf4fe88c20038b3e96c", "HeroRank_roadhog_32": "5a9f3fc017d009006904b630", "HeroRank_zenyatta_20": "5a9f3fbe17d009006904b5da", "HeroRank_bastion_6": "5a9f3fbc17d009006904b55c", "HeroRank_hanzo_10": "5aa801b044d904006533ab54", "HeroRank_mccree_15": "5a9f3fbe17d009006904b5f1", "Match_10319": "5a95aafdfe88c20038b3e9fc", "HeroRank_reaper_1": "5a9f3fc317d009006904b705", "HeroRank_mercy_21": "5a9f3fc017d009006904b66c", "PlayerRank_50": "5a9f3fb8a22b9d00456ade39", "PlayerRank_41": "5a9f3fb8a22b9d00456ade30", "CompositionUsage_ddsstt_maps_king's_row": "5a9d30e19f54541bcd381ca5", "HeroRank_soldier-76_22": "5a9f3fbc17d009006904b553", "CompositionUsage_ddsttt_maps_hollywood": "5a9d30e29f54541bcd381ce3", "CompositionUsage_ddssst_maps_lijiang_tower": "5aac795f9f545448cf2b4e1d", "Match_10490": "5a95aafffe88c20038b3ea89", "PlayerPickRate_4413": "5aac79baee920a00452a34ae", "PlayerRank_70": "5a9f3fb9a22b9d00456ade4d", "HeroRank_pharah_24": "5aa801b744d904006533aba3", "HeroRank_soldier-76_27": "5a9f3fbf17d009006904b60f", "HeroRank_winston_13": "5a9f3fc217d009006904b6e2", "HeroRank_dva_5": "5a9f3fbc17d009006904b56e", "HeroRank_reaper_13": "5aa1952f44d9040044fa6627", "HeroRank_junkrat_5": "5a9f3fbc17d009006904b57f", "HeroRank_pharah_20": "5a9f3fc117d009006904b6b4", "HeroRank_mercy_7": "5a9f3fbb17d009006904b535", "Match_10575": "5a95aafcfe88c20038b3e9cd", "CompositionUsage_ddssst_maps_eichenwalde": "5a9d30e29f54541bcd381cbc", "Match_10380": "5a95aafefe88c20038b3ea4b", "Match_10301": "5a95aafdfe88c20038b3e9e9", "Match_10574": "5a95aafcfe88c20038b3e9cc", "CompositionUsage_dssttt_maps_king's_row": "5a9d30e19f54541bcd381ca6", "CompositionUsage_ddsttt_maptypes_control": "5a9d30e19f54541bcd381c67", "HeroRank_genji_19": "5a9f3fc317d009006904b700", "HeroRank_roadhog_23": "5a9f3fbb17d009006904b545", "Match_10532": "5a95aafbfe88c20038b3e98c", "HeroRank_roadhog_22": "5a9f3fc017d009006904b644", "HeroRank_reaper_12": "5aa1953244d9040044fa662a", "CompositionUsage_dssstt_maps_lijiang_tower": "5a9d30e29f54541bcd381cdd", "PlayerRank_11": "5a9f3fb8a22b9d00456ade11", "HeroRank_widowmaker_5": "5a9f3fc217d009006904b6d8", "PlayerPickRate_4019": "5aac79b9ee920a00452a3484", "HeroRank_d.va_9": "5a9d66059f545467f5c6d7f6", "CompositionUsage_dddsst_maps_hollywood": "5a9d30e29f54541bcd381ce4", "PlayerPickRate_4025": "5aac79b8ee920a00452a3449", "HeroRank_dva_8": "5a9f3fbe17d009006904b5db", "CompositionUsage_dddsst_maps_volskaya_industries": "5a9d30e19f54541bcd381c9b", "PlayerRank_14": "5a9f3fb8a22b9d00456ade15", "HeroRank_tracer_26": "5a9f3fc317d009006904b708", "Rank_12": "5a95aaf5ee920a788075a6f5", "Match_10572": "5a95aafcfe88c20038b3e9ca", "Match_10477": "5a95aafefe88c20038b3ea7c", "CompositionUsage_dssttt_maps_lijiang_tower": "5a9d30e29f54541bcd381cd8", "Match_10375": "5a95aafefe88c20038b3ea46", "HeroRank_soldier: 76_7": "5a9d66059f545467f5c6d7f3", "CompositionUsage_ddsstt_maps_oasis": "5a9d30e29f54541bcd381cc7", "CompositionUsage_dssttt_maps_oasis": "5a9d30e29f54541bcd381cc8", "PlayerRank_79": "5a9f3fb9a22b9d00456ade56", "HeroRank_zarya_17": "5a9f3fbd17d009006904b5a4", "HeroRank_d.va_8": "5a9d66059f545467f5c6d7c6", "HeroRank_junkrat_22": "5aa1953044d9040044fa6628", "Match_10316": "5a95aafdfe88c20038b3e9f9", "HeroRank_mei_4": "5aac79b79f5454250d886c33", "HeroRank_winston_16": "5a9f3fc317d009006904b70c", "Match_10227": "5a95aafcfe88c20038b3e995", "Match_10345": "5a95aafdfe88c20038b3ea26", "PlayerRank_65": "5a9f3fb9a22b9d00456ade48", "Match_10376": "5a95aafefe88c20038b3ea47", "Match_10475": "5a95aafefe88c20038b3ea7a", "PlayerPickRate_3503": "5aac79b9ee920a00452a3478", "CompositionUsage_dddsst_allmaps_all_maps": "5a9d30e09f54541bcd381c46", "Match_10355": "5a95aafefe88c20038b3ea30", "PlayerRank_9": "5a9f3fb8a22b9d00456ade0f", "PlayerRank_94": "5a9f3fb9a22b9d00456ade67", "PlayerPickRate_4666": "5aac79b9ee920a00452a347e", "HeroRank_moira_10": "5a9f3fbc17d009006904b574", "Match_10469": "5a95aafefe88c20038b3ea74", "HeroRank_genji_17": "5a9f3fc117d009006904b6b8", "PlayerRank_36": "5a9f3fb8a22b9d00456ade2b", "HeroRank_roadhog_31": "5a9f3fbd17d009006904b5af", "PlayerPickRate_3969": "5aac79b9ee920a00452a3471", "HeroRank_junkrat_14": "5a9f3fc117d009006904b6b9", "Match_10534": "5a95aafbfe88c20038b3e98e", "PlayerRank_81": "5a9f3fb9a22b9d00456ade58", "Match_10489": "5a95aafffe88c20038b3ea88", "HeroRank_dva_3": "5a9f3fbe17d009006904b5ec", "PlayerRank_62": "5a9f3fb8a22b9d00456ade45", "HeroRank_lucio_12": "5a9f3fbd17d009006904b5b3", "Match_10255": "5a95aafcfe88c20038b3e9b1", "HeroRank_tracer_30": "5aac79b69f5454250d886c2e", "CompositionUsage_sstttt_maps_horizon_lunar_colony": "5a9d30e29f54541bcd381cd0", "HeroRank_genji_10": "5a9f3fbf17d009006904b603", "CompositionUsage_dddstt_maps_route_66": "5a9d30e29f54541bcd381caf", "Rank_8": "5a95aaf5ee920a788075a6f1", "HeroRank_reaper_7": "5a9f3fbf17d009006904b606", "Match_10293": "5a95aafdfe88c20038b3e9e0", "CompositionUsage_ddddst_maps_horizon_lunar_colony": "5a9d30e29f54541bcd381cd4", "HeroRank_mercy_25": "5a9f3fc117d009006904b6b1", "PlayerRank_6": "5a9f3fb8a22b9d00456ade0b", "HeroRank_sombra_19": "5a9f3fc117d009006904b689", "CompositionUsage_ddsstt_maps_numbani": "5a9d30e19f54541bcd381c91", "HeroRank_tracer_3": "5a9f3fbe17d009006904b5e1", "Match_10299": "5a95aafdfe88c20038b3e9e7", "HeroRank_widowmaker_29": "5aac79b19f5454250d886c0d", "HeroRank_winston_11": "5a9f3fc217d009006904b6df", "CompositionUsage_sstttt_maps_junkertown": "5a9d30e29f54541bcd381cc3", "HeroRank_soldier-76_24": "5a9f3fbe17d009006904b5e0", "CompositionUsage_dstttt_allmaps_all_maps": "5a9d30e09f54541bcd381c49", "HeroRank_ana_17": "5a9f3fc117d009006904b6af", "HeroRank_hanzo_9": "5a9f3fbb17d009006904b53d", "HeroRank_d.va_1": "5a9d66029f545467f5c6d71a", "CompositionUsage_ddssst_maps_ilios": "5a9d30e19f54541bcd381c8d", "PlayerPickRate_4664": "5aac79b9ee920a00452a34a6", "HeroRank_orisa_11": "5a9f3fc217d009006904b6c6", "HeroRank_widowmaker_12": "5a9f3fc017d009006904b664", "HeroRank_genji_16": "5a9f3fc117d009006904b68c", "Match_10484": "5a95aafffe88c20038b3ea83", "HeroRank_lucio_14": "5a9f3fc017d009006904b649", "Match_10622": "5a95aafffe88c20038b3ea8b", "TeamHeroUsage_4405": "5a9d578cd50eee2ea31b70f4", "HeroRank_junkrat_12": "5a9f3fc117d009006904b676", "CompositionUsage_dssstt_maps_nepal": "5a9d30e19f54541bcd381ca3", "CompositionUsage_dddttt_maps_ilios": "5a9d30e19f54541bcd381c8f", "HeroRank_tracer_4": "5a9f3fbc17d009006904b582", "HeroRank_soldier-76_32": "5a9f3fbb17d009006904b54b", "HeroRank_winston_7": "5a9f3fc017d009006904b66a", "HeroRank_zenyatta_19": "5a9f3fc217d009006904b6cb", "HeroRank_moira_9": "5a9f3fc117d009006904b688", "PlayerPickRate_4622": "5aac79b9ee920a00452a346a", "Match_10483": "5a95aafefe88c20038b3ea82", "Match_10335": "5a95aafdfe88c20038b3ea1b", "HeroRank_sombra_18": "5a9f3fbc17d009006904b587", "HeroRank_widowmaker_3": "5a9f3fbc17d009006904b57a", "PlayerRank_85": "5a9f3fb9a22b9d00456ade5c", "HeroRank_ana_28": "5aac79ae9f5454250d886bf6", "Match_10586": "5a95aafdfe88c20038b3ea15", "HeroRank_moira_19": "5aa801b644d904006533ab88", "HeroRank_tracer_23": "5a9f3fc217d009006904b6fb", "PlayerRank_100": "5a9f3fb9a22b9d00456ade6d", "Match_10571": "5a95aafcfe88c20038b3e9c9", "Match_10374": "5a95aafefe88c20038b3ea45", "Match_10573": "5a95aafcfe88c20038b3e9cb", "Match_10303": "5a95aafdfe88c20038b3e9eb", "PlayerPickRate_4000": "5aac79b9ee920a00452a3462", "CompositionUsage_dddstt_allmaps_all_maps": "5a9d30e09f54541bcd381c42", "HeroRank_orisa_16": "5a9f3fc317d009006904b71d", "PlayerRank_32": "5a9f3fb8a22b9d00456ade27", "HeroRank_zenyatta_16": "5a9f3fc117d009006904b68a", "HeroRank_mccree_7": "5a9f3fc017d009006904b660", "TeamHeroUsage_4525": "5a9d578cd50eee2ea31b70ec", "PlayerRank_99": "5a9f3fb9a22b9d00456ade6c", "HeroRank_hanzo_3": "5a9f3fbd17d009006904b59b", "PlayerPickRate_4640": "5aac79baee920a00452a34ad", "PlayerPickRate_4617": "5aac79b9ee920a00452a345d", "HeroRank_junkrat_13": "5a9f3fc117d009006904b67c", "Match_10594": "5a95aafefe88c20038b3ea52", "Match_10267": "5a95aafcfe88c20038b3e9bd", "HeroRank_junkrat_17": "5a9f3fc217d009006904b6f6", "HeroRank_widowmaker_14": "5a9f3fc117d009006904b691", "PlayerRank_3": "5a9f3fb8a22b9d00456ade08", "HeroRank_ana_20": "5a9f3fbc17d009006904b561", "HeroRank_zarya_13": "5a9f3fc117d009006904b681", "HeroRank_reinhardt_14": "5a9f3fc317d009006904b71e", "CompositionUsage_ddsttt_maps_numbani": "5a9d30e19f54541bcd381c95", "HeroRank_moira_18": "5aa1953644d9040044fa6634", "TeamHeroUsage_4407": "5a9d578cd50eee2ea31b70f2", "HeroRank_ana_9": "5a9f3fbb17d009006904b530", "Match_10623": "5a95aafffe88c20038b3ea8c", "Match_10280": "5a95aafcfe88c20038b3e9d3", "HeroRank_soldier-76_19": "5a9f3fbe17d009006904b5d3", "HeroRank_widowmaker_25": "5a9f3fc217d009006904b6fc", "Match_10245": "5a95aafcfe88c20038b3e9a7", "Match_10445": "5a95aafefe88c20038b3ea5c", "Match_10353": "5a95aafdfe88c20038b3ea2e", "HeroRank_ana_6": "5a9f3fbb17d009006904b536", "HeroRank_mercy_4": "5a9f3fc217d009006904b6bc", "HeroRank_orisa_5": "5a9f3fbc17d009006904b57b", "PlayerRank_27": "5a9f3fb8a22b9d00456ade22", "CompositionUsage_dddsst_maps_junkertown": "5a9d30e29f54541bcd381cc4", "PlayerPickRate_4647": "5aac79baee920a00452a34aa", "HeroRank_d.va_10": "5a9d66069f545467f5c6d803", "Match_10361": "5a95aafefe88c20038b3ea37", "HeroRank_genji_5": "5a9f3fc017d009006904b635", "HeroRank_pharah_10": "5a9f3fbe17d009006904b5d1", "HeroRank_lucio_4": "5a9f3fbd17d009006904b59c", "Match_10486": "5a95aafffe88c20038b3ea85", "Match_10629": "5a95aafffe88c20038b3ea92", "HeroRank_soldier-76_15": "5a9f3fc017d009006904b645", "HeroRank_doomfist_4": "5a9f3fc317d009006904b6ff", "Match_10346": "5a95aafdfe88c20038b3ea27", "CompositionUsage_dssstt_maptypes_assault": "5a9d30e09f54541bcd381c60", "Match_10323": "5a95aafdfe88c20038b3ea05", "HeroRank_reinhardt_7": "5a9f3fc217d009006904b6f3", "HeroRank_mccree_17": "5a9f3fc017d009006904b670", "HeroRank_bastion_8": "5a9f3fbc17d009006904b562", "CompositionUsage_ddsttt_maps_ilios": "5a9d30e19f54541bcd381c8b", "HeroRank_soldier-76_5": "5a9f3fc117d009006904b67e", "HeroRank_zenyatta_1": "5a9f3fbd17d009006904b5bf", "HeroRank_zarya_1": "5a9f3fc117d009006904b679", "CompositionUsage_sstttt_maps_nepal": "5aac795f9f545448cf2b4e1b", "HeroRank_mercy_3": "5a9f3fbf17d009006904b5f8", "Match_10447": "5a95aafefe88c20038b3ea5e", "HeroRank_zenyatta_22": "5a9f3fc017d009006904b66e", "PlayerRank_46": "5a9f3fb8a22b9d00456ade35", "HeroRank_genji_8": "5a9f3fbe17d009006904b5ee", "HeroRank_d.va_19": "5a9d66089f545467f5c6d8c0", "Match_10535": "5a95aafbfe88c20038b3e98f", "PlayerPickRate_3384": "5aac79baee920a00452a34b4", "HeroRank_zarya_19": "5a9f3fc217d009006904b6ce", "Competitor_4405": "5a95aaf4fe88c20038b3e96d", "HeroRank_sombra_16": "5a9f3fbe17d009006904b5d9", "Match_10233": "5a95aafcfe88c20038b3e99b", "Rank_11": "5a95aaf5ee920a788075a6f4", "HeroRank_pharah_23": "5a9f3fc317d009006904b711", "HeroRank_pharah_2": "5a9f3fc117d009006904b677", "HeroRank_d.va_15": "5a9d66039f545467f5c6d768", "Match_10356": "5a95aafefe88c20038b3ea31", "Match_10342": "5a95aafdfe88c20038b3ea22", "CompositionUsage_dssstt_maptypes_control": "5a9d30e19f54541bcd381c68", "HeroRank_hanzo_4": "5a9f3fc017d009006904b66f", "HeroRank_soldier: 76_32": "5a9d66029f545467f5c6d723", "Match_10621": "5a95aafffe88c20038b3ea8a", "Match_10247": "5a95aafcfe88c20038b3e9a9", "CompositionUsage_dddstt_maps_ilios": "5a9d30e19f54541bcd381c89", "HeroRank_dva_23": "5aac79b09f5454250d886c07", "HeroRank_genji_1": "5a9f3fc017d009006904b64d", "HeroRank_mccree_16": "5a9f3fc217d009006904b6e3", "HeroRank_ana_22": "5a9f3fbd17d009006904b596", "Match_10444": "5a95aafefe88c20038b3ea5b", "PlayerPickRate_4105": "5aac79b8ee920a00452a3456", "HeroRank_orisa_6": "5a9f3fc317d009006904b720", "Match_10350": "5a95aafdfe88c20038b3ea2b", "PlayerPickRate_4633": "5aac79b9ee920a00452a3459", "CompositionUsage_dddsst_maps_hanamura": "5a9d30e39f54541bcd381cea", "HeroRank_zarya_15": "5a9f3fc017d009006904b634", "HeroRank_ana_1": "5a9f3fbc17d009006904b554", "HeroRank_d.va_5": "5a9d66039f545467f5c6d74e", "HeroRank_zenyatta_2": "5a9f3fbb17d009006904b52f", "Match_10470": "5a95aafefe88c20038b3ea75", "HeroRank_orisa_17": "5a9f3fc017d009006904b665", "HeroRank_mccree_1": "5a9f3fc017d009006904b63c", "Rank_5": "5a95aaf5ee920a788075a6ee", "HeroRank_sombra_17": "5a9f3fbf17d009006904b61f", "HeroRank_zarya_14": "5a9f3fc217d009006904b6d2", "HeroRank_moira_11": "5a9f3fbb17d009006904b544", "Match_10283": "5a95aafcfe88c20038b3e9d6", "HeroRank_soldier: 76_12": "5a9d66089f545467f5c6d89a", "Match_10597": "5a95aafefe88c20038b3ea55", "HeroRank_bastion_3": "5a9f3fc117d009006904b685", "HeroRank_reinhardt_1": "5a9f3fc217d009006904b6db", "HeroRank_sombra_6": "5a9f3fc317d009006904b717", "HeroRank_moira_15": "5a9f3fbd17d009006904b59f", "HeroRank_soldier: 76_16": "5a9d66049f545467f5c6d7a1", "HeroRank_tracer_20": "5a9f3fc217d009006904b6d7", "HeroRank_junkrat_16": "5a9f3fbf17d009006904b61c", "Rank_10": "5a95aaf5ee920a788075a6f3", "HeroRank_lucio_3": "5a9f3fbd17d009006904b597", "Match_10451": "5a95aafefe88c20038b3ea62", "PlayerPickRate_4138": "5aac79b9ee920a00452a3481", "PlayerPickRate_4639": "5aac79b9ee920a00452a3461", "TeamPickRate_HOU": "5aac79bb17d009688742069a", "Match_10260": "5a95aafcfe88c20038b3e9b6", "CompositionUsage_sstttt_maptypes_hybrid": "5a9d30e19f54541bcd381c71", "PlayerRank_56": "5a9f3fb8a22b9d00456ade3f", "Match_10289": "5a95aafdfe88c20038b3e9dc", "HeroRank_reaper_9": "5a9f3fc217d009006904b6e5", "HeroRank_tracer_14": "5a9f3fc017d009006904b63d", "Match_10548": "5a95aafffe88c20038b3ea97", "PlayerPickRate_4605": "5aac79b9ee920a00452a3499", "HeroRank_mercy_10": "5a9f3fc117d009006904b687", "HeroRank_zarya_6": "5a9f3fbc17d009006904b54d", "HeroRank_mccree_4": "5a9f3fc017d009006904b64f", "HeroRank_soldier-76_17": "5a9f3fc217d009006904b6fa", "HeroRank_soldier-76_33": "5aa801b444d904006533ab74", "CompositionUsage_sstttt_maps_lijiang_tower": "5a9d30e29f54541bcd381cda", "HeroRank_soldier-76_16": "5a9f3fbd17d009006904b5ba", "Match_10334": "5a95aafdfe88c20038b3ea1a", "PlayerRank_69": "5a9f3fb9a22b9d00456ade4c", "CompositionUsage_ddsstt_maptypes_control": "5a9d30e09f54541bcd381c62", "PlayerRank_93": "5a9f3fb9a22b9d00456ade65", "PlayerPickRate_4618": "5aac79b9ee920a00452a34a8", "HeroRank_lucio_2": "5a9f3fbb17d009006904b531", "HeroRank_soldier: 76_29": "5a9d660a9f545467f5c6d911", "HeroRank_mercy_11": "5a9f3fbd17d009006904b5b7", "HeroRank_orisa_4": "5a9f3fbe17d009006904b5c8", "Match_10231": "5a95aafcfe88c20038b3e999", "Match_10291": "5a95aafdfe88c20038b3e9de", "CompositionUsage_ddssst_maptypes_hybrid": "5a9d30e19f54541bcd381c76", "HeroRank_orisa_13": "5a9f3fc217d009006904b6f2", "Match_10368": "5a95aafefe88c20038b3ea3e", "PlayerPickRate_4020": "5aac79b9ee920a00452a3479", "HeroRank_soldier: 76_21": "5a9d66079f545467f5c6d83e", "HeroRank_pharah_14": "5a9f3fc217d009006904b6ba", "Match_10370": "5a95aafefe88c20038b3ea41", "HeroRank_reaper_14": "5aa801b444d904006533ab73", "PlayerPickRate_4623": "5aac79b9ee920a00452a348a", "CompositionUsage_sstttt_maptypes_assault": "5a9d30e09f54541bcd381c5b", "League_61": "5a95aaf3ac502e0032ddb51b", "HeroRank_zenyatta_7": "5a9f3fbc17d009006904b560", "Match_10284": "5a95aafcfe88c20038b3e9d7", "CompositionUsage_ddsttt_maps_king's_row": "5a9d30e19f54541bcd381cab", "HeroRank_d.va_17": "5a9d66089f545467f5c6d8bd", "HeroRank_tracer_10": "5a9f3fc017d009006904b632", "HeroRank_lucio_1": "5a9f3fbb17d009006904b534", "HeroRank_mccree_5": "5a9f3fbc17d009006904b577", "Match_10453": "5a95aafefe88c20038b3ea64", "HeroRank_genji_15": "5a9f3fbe17d009006904b5ce", "HeroRank_junkrat_23": "5aa801b344d904006533ab70", "HeroRank_widowmaker_9": "5a9f3fbd17d009006904b5a9", "HeroRank_zenyatta_12": "5a9f3fbd17d009006904b5bc", "HeroRank_zenyatta_9": "5a9f3fbc17d009006904b55a", "HeroRank_roadhog_27": "5a9f3fc317d009006904b716", "HeroRank_tracer_25": "5a9f3fc017d009006904b646", "CompositionUsage_ddsttt_maps_junkertown": "5a9d30e29f54541bcd381cc0", "HeroRank_pharah_16": "5a9f3fc017d009006904b661", "PlayerRank_22": "5a9f3fb8a22b9d00456ade1d", "Match_10298": "5a95aafdfe88c20038b3e9e6", "HeroRank_widowmaker_18": "5a9f3fbe17d009006904b5ea", "HeroRank_lucio_19": "5a9f3fbd17d009006904b5c4", "PlayerPickRate_4126": "5aac79b9ee920a00452a3477", "HeroRank_mercy_17": "5a9f3fbd17d009006904b598", "HeroRank_lucio_6": "5a9f3fbc17d009006904b584", "CompositionUsage_ddddst_maps_ilios": "5a9d30e19f54541bcd381c8e", "HeroRank_soldier: 76_26": "5a9d66089f545467f5c6d87f", "HeroRank_winston_14": "5a9f3fc217d009006904b6dc", "HeroRank_soldier: 76_5": "5a9d66079f545467f5c6d86b", "HeroRank_d.va_13": "5a9d66079f545467f5c6d872", "HeroRank_winston_15": "5a9f3fc317d009006904b70f", "PlayerPickRate_4663": "5aac79b9ee920a00452a34a5", "PlayerRank_24": "5a9f3fb8a22b9d00456ade1f", "Stage_0": "5a95aaf8fe88c20038b3e977", "HeroRank_roadhog_6": "5a9f3fbf17d009006904b5fc", "Match_10251": "5a95aafcfe88c20038b3e9ad", "PlayerPickRate_4646": "5aac79b9ee920a00452a3468", "CompositionUsage_dssttt_maptypes_escort": "5a9d30e09f54541bcd381c51", "HeroRank_zenyatta_15": "5a9f3fc317d009006904b719", "Rank_2": "5a95aaf5ee920a788075a6eb", "PlayerRank_52": "5a9f3fb8a22b9d00456ade3b", "HeroRank_zenyatta_24": "5a9f3fbd17d009006904b595", "HeroRank_soldier-76_35": "5aa801b044d904006533ab55", "HeroRank_roadhog_7": "5a9f3fbc17d009006904b54f", "Match_10238": "5a95aafcfe88c20038b3e9a0", "HeroRank_roadhog_11": "5a9f3fbc17d009006904b55f", "HeroRank_widowmaker_19": "5a9f3fc017d009006904b63f", "CompositionUsage_ddsttt_maps_temple_of_anubis": "5a9d30e19f54541bcd381c84", "HeroRank_tracer_8": "5a9f3fbf17d009006904b629", "HeroRank_pharah_18": "5a9f3fbd17d009006904b5a1", "Match_10297": "5a95aafdfe88c20038b3e9e5", "TeamHeroUsage_4403": "5a9d578cd50eee2ea31b70eb", "Match_10459": "5a95aafefe88c20038b3ea6a", "Competitor_4402": "5a95aaf4fe88c20038b3e96a", "CompositionUsage_ddssst_maptypes_escort": "5a9d30e09f54541bcd381c57", "HeroRank_mercy_14": "5a9f3fbc17d009006904b585", "PlayerRank_49": "5a9f3fb8a22b9d00456ade38", "HeroRank_dva_22": "5aa801b244d904006533ab6e", "HeroRank_reaper_2": "5a9f3fc217d009006904b6d5", "Match_10305": "5a95aafdfe88c20038b3e9ed", "CompositionUsage_ddsstt_maptypes_assault": "5a9d30e09f54541bcd381c58", "HeroRank_mccree_25": "5a9f3fc317d009006904b702", "Competitor_4408": "5a95aaf5fe88c20038b3e970", "Match_10568": "5a95aafcfe88c20038b3e9c6", "HeroRank_soldier: 76_19": "5a9d66049f545467f5c6d7bd", "HeroRank_genji_14": "5a9f3fc217d009006904b6bf", "Match_10481": "5a95aafefe88c20038b3ea80", "CompositionUsage_dddstt_maps_junkertown": "5a9d30e29f54541bcd381cbf", "HeroRank_zenyatta_10": "5a9f3fbc17d009006904b576", "Rank_7": "5a95aaf5ee920a788075a6f0", "Match_10354": "5a95aafdfe88c20038b3ea2f", "HeroRank_mercy_20": "5a9f3fbd17d009006904b5c2", "HeroRank_widowmaker_4": "5a9f3fbf17d009006904b60a", "HeroRank_winston_12": "5a9f3fc217d009006904b6f4", "HeroRank_soldier-76_13": "5a9f3fbf17d009006904b628", "HeroRank_ana_8": "5a9f3fbb17d009006904b541", "HeroRank_lucio_20": "5a9f3fc217d009006904b6ed", "PlayerRank_19": "5a9f3fb8a22b9d00456ade1a", "PlayerRank_53": "5a9f3fb8a22b9d00456ade3c", "Match_10258": "5a95aafcfe88c20038b3e9b4", "PlayerPickRate_3987": "5aac79b8ee920a00452a3446", "Match_10285": "5a95aafcfe88c20038b3e9d8", "CompositionUsage_ddsstt_maps_temple_of_anubis": "5a9d30e19f54541bcd381c7d", "PlayerRank_35": "5a9f3fb8a22b9d00456ade2a", "PlayerRank_73": "5a9f3fb9a22b9d00456ade50", "Rank_6": "5a95aaf5ee920a788075a6ef", "Match_10263": "5a95aafcfe88c20038b3e9b9", "HeroRank_zenyatta_6": "5a9f3fbc17d009006904b566", "HeroRank_tracer_28": "5aa801b544d904006533ab7f", "HeroRank_zarya_18": "5a9f3fc117d009006904b692", "PlayerPickRate_4095": "5aac79b9ee920a00452a347b", "HeroRank_widowmaker_26": "5a9f3fc117d009006904b673", "HeroRank_zarya_10": "5a9f3fbc17d009006904b573", "HeroRank_soldier-76_1": "5a9f3fc117d009006904b69f", "PlayerPickRate_4143": "5aac79b9ee920a00452a3474", "HeroRank_genji_11": "5a9f3fbf17d009006904b61b", "CompositionUsage_ddsstt_maps_horizon_lunar_colony": "5a9d30e29f54541bcd381cce", "PlayerPickRate_4104": "5aac79b9ee920a00452a3457", "HeroRank_sombra_24": "5aa801b144d904006533ab57", "HeroRank_sombra_1": "5a9f3fbe17d009006904b5d4", "CompositionUsage_ddsstt_maps_dorado": "5a9d30e19f54541bcd381c77", "Match_10235": "5a95aafcfe88c20038b3e99d", "HeroRank_junkrat_20": "5a9f3fbe17d009006904b5dd", "HeroRank_hanzo_6": "5a9f3fc217d009006904b6c0", "HeroRank_reaper_11": "5a9f3fbe17d009006904b5e6", "PlayerRank_60": "5a9f3fb8a22b9d00456ade43", "Match_10244": "5a95aafcfe88c20038b3e9a6", "HeroRank_mccree_26": "5a9f3fc317d009006904b710", "TeamHeroUsage_4402": "5a9d578cd50eee2ea31b70f0", "CompositionUsage_dddstt_maps_numbani": "5a9d30e19f54541bcd381c93", "CompositionUsage_ddddtt_allmaps_all_maps": "5a9d30e09f54541bcd381c4c", "Match_10536": "5a95aafbfe88c20038b3e990", "CompositionUsage_ddddst_maptypes_assault": "5a9d30e09f54541bcd381c5d", "CompositionUsage_sstttt_maps_king's_row": "5a9d30e19f54541bcd381ca8", "HeroRank_winston_6": "5a9f3fc017d009006904b667", "Stage_5": "5a95aafafe88c20038b3e97c", "PlayerPickRate_4626": "5aac79b8ee920a00452a3447", "CompositionUsage_sssttt_maps_ilios": "5a9d30e19f54541bcd381c8c", "HeroRank_ana_26": "5aac79b29f5454250d886c1a", "HeroRank_roadhog_18": "5a9f3fc217d009006904b6cd", "HeroRank_sombra_21": "5a9f3fc217d009006904b6ef", "CompositionUsage_ddsttt_maps_watchpoint:_gibraltar": "5aa801a99f54540045656587", "HeroRank_dva_6": "5a9f3fbc17d009006904b571", "HeroRank_roadhog_17": "5a9f3fbb17d009006904b52e", "HeroRank_moira_5": "5a9f3fbd17d009006904b5c6", "PlayerPickRate_4624": "5aac79b9ee920a00452a348c", "PlayerPickRate_4632": "5aac79b8ee920a00452a3452", "Match_10526": "5a95aafbfe88c20038b3e986", "CompositionUsage_dssttt_maps_ilios": "5a9d30e19f54541bcd381c87", "CompositionUsage_ddsstt_maps_hanamura": "5a9d30e29f54541bcd381ce7", "Match_10446": "5a95aafefe88c20038b3ea5d", "Match_10525": "5a95aafbfe88c20038b3e985", "TeamPickRate_LDN": "5aac79bb17d0096887420698", "HeroRank_zarya_22": "5a9f3fc217d009006904b6eb", "HeroRank_soldier: 76_13": "5a9d66069f545467f5c6d814", "Match_10313": "5a95aafdfe88c20038b3e9f6", "CompositionUsage_dddstt_maps_hollywood": "5a9d30e29f54541bcd381ce2", "Match_10465": "5a95aafefe88c20038b3ea70", "HeroRank_sombra_12": "5a9f3fc017d009006904b654", "HeroRank_winston_8": "5a9f3fc117d009006904b6a7", "PlayerPickRate_4644": "5aac79b9ee920a00452a345f", "HeroRank_soldier-76_7": "5a9f3fbf17d009006904b608", "Match_10366": "5a95aafefe88c20038b3ea3c", "CompositionUsage_dssstt_maps_volskaya_industries": "5a9d30e19f54541bcd381c9d", "PlayerRank_10": "5a9f3fb8a22b9d00456ade10", "PlayerRank_101": "5a9f3fb9a22b9d00456ade6e", "HeroRank_d.va_21": "5a9d660a9f545467f5c6d919", "PlayerRank_5": "5a9f3fb8a22b9d00456ade0a", "HeroRank_zarya_3": "5a9f3fc017d009006904b63b", "PlayerRank_47": "5a9f3fb8a22b9d00456ade36", "PlayerRank_33": "5a9f3fb8a22b9d00456ade28", "Match_10474": "5a95aafefe88c20038b3ea79", "Match_10589": "5a95aafefe88c20038b3ea4d", "HeroRank_tracer_12": "5a9f3fc017d009006904b65e", "HeroRank_tracer_32": "5aac79b79f5454250d886c31", "CompositionUsage_dssttt_maptypes_assault": "5a9d30e09f54541bcd381c5a", "PlayerPickRate_4655": "5aac79b9ee920a00452a3480", "PlayerRank_26": "5a9f3fb8a22b9d00456ade21", "HeroRank_mccree_23": "5a9f3fc117d009006904b695", "PlayerRank_13": "5a9f3fb8a22b9d00456ade14", "CompositionUsage_ddsttt_maptypes_assault": "5a9d30e09f54541bcd381c5f", "PlayerPickRate_4098": "5aac79b8ee920a00452a3454", "HeroRank_lucio_23": "5aac79b29f5454250d886c16", "HeroRank_lucio_15": "5a9f3fc117d009006904b6b0", "HeroRank_tracer_19": "5a9f3fc017d009006904b655", "HeroRank_sombra_22": "5a9f3fbc17d009006904b565", "HeroRank_soldier-76_25": "5a9f3fc217d009006904b6e7", "Match_10232": "5a95aafcfe88c20038b3e99a", "Match_10236": "5a95aafcfe88c20038b3e99e", "CompositionUsage_ddsstt_maptypes_escort": "5a9d30e09f54541bcd381c4e", "HeroRank_soldier-76_4": "5a9f3fc017d009006904b662", "HeroRank_winston_4": "5a9f3fbd17d009006904b58f", "Match_10461": "5a95aafefe88c20038b3ea6c", "HeroRank_genji_12": "5a9f3fc017d009006904b640", "HeroRank_pharah_4": "5a9f3fbe17d009006904b5e5", "PlayerRank_37": "5a9f3fb8a22b9d00456ade2c", "PlayerRank_25": "5a9f3fb8a22b9d00456ade20", "Match_10337": "5a95aafdfe88c20038b3ea1d", "HeroRank_soldier-76_2": "5a9f3fbc17d009006904b581", "HeroRank_mccree_9": "5a9f3fc017d009006904b62e", "CompositionUsage_dssstt_allmaps_all_maps": "5a9d30e09f54541bcd381c48", "CompositionUsage_ddsstt_maps_ilios": "5a9d30e19f54541bcd381c86", "PlayerPickRate_4652": "5aac79b9ee920a00452a349a", "HeroRank_soldier-76_12": "5a9f3fc117d009006904b6a9", "HeroRank_widowmaker_6": "5a9f3fc017d009006904b633", "PlayerPickRate_4608": "5aac79b9ee920a00452a346b", "CompositionUsage_dddsst_maps_temple_of_anubis": "5a9d30e19f54541bcd381c81", "HeroRank_soldier-76_18": "5a9f3fbf17d009006904b5f4", "HeroRank_lucio_8": "5a9f3fbd17d009006904b5b1", "PlayerPickRate_3983": "5aac79b8ee920a00452a3444", "HeroRank_dva_11": "5a9f3fbf17d009006904b612", "TeamPickRate_PHI": "5aac79bb17d009688742069b", "Match_10240": "5a95aafcfe88c20038b3e9a2", "HeroRank_zenyatta_11": "5a9f3fbf17d009006904b611", "CompositionUsage_ddsttt_maps_route_66": "5a9d30e29f54541bcd381cb2", "HeroRank_zarya_21": "5a9f3fbc17d009006904b569", "PlayerPickRate_4612": "5aac79b9ee920a00452a349b", "PlayerRank_80": "5a9f3fb9a22b9d00456ade57", "HeroRank_tracer_22": "5a9f3fbf17d009006904b620", "HeroRank_mccree_6": "5a9f3fc117d009006904b6a8", "Match_10290": "5a95aafdfe88c20038b3e9dd", "HeroRank_moira_17": "5a9f3fbb17d009006904b539", "PlayerPickRate_3479": "5aac79b9ee920a00452a3482", "PlayerRank_72": "5a9f3fb9a22b9d00456ade4f", "HeroRank_zarya_2": "5a9f3fc217d009006904b6fd", "HeroRank_pharah_6": "5a9f3fc017d009006904b643", "Match_10487": "5a95aafffe88c20038b3ea86", "HeroRank_soldier-76_8": "5a9f3fc117d009006904b678", "Match_10364": "5a95aafefe88c20038b3ea3a", "HeroRank_junkrat_9": "5a9f3fbe17d009006904b5f0", "HeroRank_bastion_7": "5a9f3fc117d009006904b693", "HeroRank_pharah_13": "5a9f3fc117d009006904b67d", "CompositionUsage_dssstt_maps_eichenwalde": "5a9d30e29f54541bcd381cba", "Match_10468": "5a95aafefe88c20038b3ea73", "CompositionUsage_dddsst_maps_horizon_lunar_colony": "5a9d30e29f54541bcd381cd2", "Match_10540": "5a95aafdfe88c20038b3ea17", "HeroRank_genji_25": "5aa1953344d9040044fa6630", "HeroRank_sombra_9": "5a9f3fbb17d009006904b53a", "CompositionUsage_dddstt_maps_dorado": "5a9d30e19f54541bcd381c7a", "HeroRank_tracer_5": "5a9f3fbc17d009006904b579", "PlayerRank_16": "5a9f3fb8a22b9d00456ade17", "HeroRank_reaper_8": "5a9f3fbe17d009006904b5d2", "PlayerPickRate_4140": "5aac79b9ee920a00452a3488", "HeroRank_tracer_1": "5a9f3fbb17d009006904b54c", "HeroRank_ana_18": "5a9f3fc217d009006904b6c9", "PlayerPickRate_4083": "5aac79b9ee920a00452a34a7", "CompositionUsage_ddddtt_maptypes_escort": "5a9d30e09f54541bcd381c56", "HeroRank_roadhog_1": "5a9f3fbe17d009006904b5e7", "HeroRank_ana_12": "5a9f3fbd17d009006904b5c3", "Match_10467": "5a95aafefe88c20038b3ea72", "HeroRank_junkrat_8": "5a9f3fc117d009006904b69b", "HeroRank_pharah_1": "5a9f3fbf17d009006904b61e", "PlayerRank_54": "5a9f3fb8a22b9d00456ade3d", "HeroRank_junkrat_19": "5a9f3fc117d009006904b694", "HeroRank_mei_1": "5a9f3fbc17d009006904b555", "Competitor_4409": "5a95aaf5fe88c20038b3e971", "PlayerRank_92": "5a9f3fb9a22b9d00456ade64", "HeroRank_zenyatta_14": "5a9f3fbf17d009006904b617", "CompositionUsage_dddsst_maps_king's_row": "5a9d30e19f54541bcd381caa", "TeamPickRate_GLA": "5aac79bb17d0096887420696", "CompositionUsage_sstttt_maps_eichenwalde": "5a9d30e29f54541bcd381cb9", "HeroRank_zenyatta_17": "5a9f3fc017d009006904b64c", "HeroRank_winston_18": "5a9f3fc317d009006904b722", "PlayerPickRate_4125": "5aac79b9ee920a00452a3473", "PlayerPickRate_3504": "5aac79b9ee920a00452a3475", "Match_10294": "5a95aafdfe88c20038b3e9e1", "Division_79": "5a95aaf3ee920a788075a6e4", "HeroRank_roadhog_35": "5a9f3fbe17d009006904b5cb", "HeroRank_pharah_22": "5a9f3fc217d009006904b6c2", "HeroRank_genji_18": "5a9f3fbe17d009006904b5dc", "HeroRank_soldier: 76_3": "5a9d66089f545467f5c6d8b5", "PlayerPickRate_4493": "5aac79baee920a00452a34b3", "Match_10584": "5a95aafdfe88c20038b3ea13", "PlayerRank_55": "5a9f3fb8a22b9d00456ade3e", "CompositionUsage_ddsstt_maps_volskaya_industries": "5a9d30e19f54541bcd381c98", "HeroRank_genji_3": "5a9f3fbc17d009006904b57e", "HeroRank_roadhog_14": "5a9f3fbc17d009006904b568", "TeamPickRate_SFS": "5aac79ba17d0096887420693", "HeroRank_lucio_7": "5a9f3fbf17d009006904b624", "Match_10450": "5a95aafefe88c20038b3ea61", "Match_10598": "5a95aafefe88c20038b3ea56", "HeroRank_orisa_2": "5a9f3fbc17d009006904b56a", "Match_10325": "5a95aafdfe88c20038b3ea0a", "HeroRank_widowmaker_28": "5aa801b544d904006533ab7a", "HeroRank_mccree_21": "5a9f3fc217d009006904b6f7", "Match_10377": "5a95aafefe88c20038b3ea48", "HeroRank_roadhog_3": "5a9f3fbf17d009006904b607", "HeroRank_orisa_15": "5a9f3fc317d009006904b70d", "Stage_1": "5a95aaf9fe88c20038b3e978", "HeroRank_ana_24": "5a9f3fc117d009006904b684", "HeroRank_doomfist_5": "5a9f3fc117d009006904b68b", "HeroRank_moira_12": "5a9f3fbc17d009006904b557", "Match_10473": "5a95aafefe88c20038b3ea78", "Match_10449": "5a95aafefe88c20038b3ea60", "PlayerPickRate_4641": "5aac79b9ee920a00452a345e", "HeroRank_roadhog_24": "5a9f3fbc17d009006904b56f", "PlayerPickRate_4643": "5aac79b9ee920a00452a3466", "PlayerRank_84": "5a9f3fb9a22b9d00456ade5b", "Match_10627": "5a95aafffe88c20038b3ea90", "PlayerPickRate_4412": "5aac79b9ee920a00452a3458", "Match_10349": "5a95aafdfe88c20038b3ea2a", "CompositionUsage_dddsst_maps_dorado": "5a9d30e19f54541bcd381c7b", "CompositionUsage_ddsttt_maptypes_escort": "5a9d30e09f54541bcd381c50", "HeroRank_dva_2": "5a9f3fbc17d009006904b54e", "HeroRank_winston_10": "5a9f3fbe17d009006904b5eb", "PlayerRank_68": "5a9f3fb9a22b9d00456ade4b", "Match_10358": "5a95aafefe88c20038b3ea33", "CompositionUsage_sstttt_maps_route_66": "5aa19526fe88c20066536ccd", "Match_10460": "5a95aafefe88c20038b3ea6b", "PlayerPickRate_3981": "5aac79b9ee920a00452a3497", "PlayerPickRate_4615": "5aac79b9ee920a00452a345c", "HeroRank_mercy_27": "5a9f3fbf17d009006904b60e", "Match_10632": "5a95aafffe88c20038b3ea95", "HeroRank_dva_17": "5a9f3fc217d009006904b6cc", "PlayerPickRate_4611": "5aac79b9ee920a00452a349c", "HeroRank_ana_11": "5a9f3fbf17d009006904b613", "HeroRank_roadhog_12": "5a9f3fbc17d009006904b572", "Match_10321": "5a95aafdfe88c20038b3ea00", "Match_10579": "5a95aafdfe88c20038b3ea0e", "HeroRank_reaper_3": "5a9f3fbb17d009006904b54a", "Division_80": "5a95aaf3ee920a788075a6e5", "HeroRank_d.va_4": "5a9d66059f545467f5c6d7d7", "HeroRank_soldier: 76_9": "5a9d66069f545467f5c6d823", "Match_10379": "5a95aafefe88c20038b3ea4a", "Match_10226": "5a95aafcfe88c20038b3e994", "CompositionUsage_dddstt_maps_watchpoint:_gibraltar": "5a9d30e39f54541bcd381cf0", "Match_10488": "5a95aafffe88c20038b3ea87", "HeroRank_soldier: 76_10": "5a9d66089f545467f5c6d8ab", "PlayerRank_89": "5a9f3fb9a22b9d00456ade60", "Match_10264": "5a95aafcfe88c20038b3e9ba", "CompositionUsage_dddstt_maps_eichenwalde": "5a9d30e29f54541bcd381cb6", "PlayerPickRate_4670": "5aac79b9ee920a00452a34a9", "Match_10224": "5a95aafcfe88c20038b3e992", "PlayerRank_76": "5a9f3fb9a22b9d00456ade53", "PlayerPickRate_4650": "5aac79b9ee920a00452a349f", "HeroRank_mercy_28": "5a9f3fbd17d009006904b5be", "HeroRank_moira_2": "5a9f3fc017d009006904b66d", "HeroRank_ana_23": "5a9f3fbe17d009006904b5d7", "CompositionUsage_dssttt_maps_junkertown": "5a9d30e29f54541bcd381cc1", "HeroRank_widowmaker_13": "5a9f3fc017d009006904b656", "Competitor_4525": "5a95aaf4fe88c20038b3e969", "Match_10480": "5a95aafefe88c20038b3ea7f", "HeroRank_zenyatta_3": "5a9f3fbb17d009006904b53b", "CompositionUsage_dddstt_maps_lijiang_tower": "5a9d30e29f54541bcd381cdb", "HeroRank_soldier: 76_4": "5a9d66079f545467f5c6d84f", "PlayerRank_20": "5a9f3fb8a22b9d00456ade1b", "Match_10479": "5a95aafefe88c20038b3ea7e", "Match_10628": "5a95aafffe88c20038b3ea91", "HeroRank_soldier-76_6": "5a9f3fc017d009006904b631", "HeroRank_widowmaker_7": "5a9f3fbd17d009006904b5a3", "PlayerRank_34": "5a9f3fb8a22b9d00456ade29", "Competitor_4406": "5a95aaf5fe88c20038b3e96e", "HeroRank_sombra_8": "5a9f3fc317d009006904b707", "CompositionUsage_dddsst_maptypes_control": "5a9d30e19f54541bcd381c66", "PlayerRank_12": "5a9f3fb8a22b9d00456ade13", "CompositionUsage_dssttt_maps_hollywood": "5a9d30e29f54541bcd381cdf", "Match_10362": "5a95aafefe88c20038b3ea38", "Match_10309": "5a95aafdfe88c20038b3e9f1", "PlayerRank_15": "5a9f3fb8a22b9d00456ade16", "HeroRank_roadhog_40": "5aac79b79f5454250d886c30", "HeroRank_genji_26": "5aa801b644d904006533ab82", "HeroRank_d.va_20": "5a9d660a9f545467f5c6d914", "PlayerRank_45": "5a9f3fb8a22b9d00456ade34", "Match_10317": "5a95aafdfe88c20038b3e9fa", "HeroRank_lucio_13": "5a9f3fbf17d009006904b601", "HeroRank_soldier-76_3": "5a9f3fc217d009006904b6c4", "HeroRank_soldier-76_26": "5a9f3fc117d009006904b68f", "PlayerPickRate_4629": "5aac79b9ee920a00452a3485", "Match_10359": "5a95aafefe88c20038b3ea34", "HeroRank_ana_16": "5a9f3fbd17d009006904b590", "PlayerRank_29": "5a9f3fb8a22b9d00456ade24", "HeroRank_zenyatta_23": "5a9f3fbd17d009006904b599", "CompositionUsage_dddstt_maps_horizon_lunar_colony": "5a9d30e29f54541bcd381ccf", "PlayerPickRate_4667": "5aac79b8ee920a00452a3453", "Match_10234": "5a95aafcfe88c20038b3e99c", "CompositionUsage_dddsst_maptypes_escort": "5a9d30e09f54541bcd381c54", "HeroRank_zarya_25": "5a9f3fc117d009006904b6ae", "HeroRank_dva_20": "5a9f3fc317d009006904b715", "HeroRank_zenyatta_5": "5a9f3fbd17d009006904b5a5", "CompositionUsage_ddsstt_maps_hollywood": "5a9d30e29f54541bcd381cde", "HeroRank_sombra_4": "5a9f3fbc17d009006904b575", "HeroRank_soldier-76_20": "5a9f3fbd17d009006904b5a2", "CompositionUsage_dssttt_maps_watchpoint:_gibraltar": "5a9d30e39f54541bcd381cef", "HeroRank_soldier-76_28": "5a9f3fc217d009006904b6d6", "HeroRank_soldier: 76_6": "5a9d66069f545467f5c6d81c", "CompositionUsage_ddsttt_maps_volskaya_industries": "5aa19525fe88c20066536ccc", "HeroRank_sombra_23": "5aa801b744d904006533ab9d", "PlayerRank_1": "5a9f3fb8a22b9d00456ade06", "Match_10570": "5a95aafcfe88c20038b3e9c8", "HeroRank_lucio_11": "5a9f3fbf17d009006904b60d", "HeroRank_soldier: 76_30": "5a9d66059f545467f5c6d7d3", "HeroRank_hanzo_2": "5a9f3fc117d009006904b67b", "Match_10378": "5a95aafefe88c20038b3ea49", "Match_10624": "5a95aafffe88c20038b3ea8d", "Match_10266": "5a95aafcfe88c20038b3e9bc", "HeroRank_widowmaker_1": "5a9f3fc017d009006904b63a", "HeroRank_orisa_18": "5aa801b544d904006533ab7c", "HeroRank_genji_27": "5aac79b59f5454250d886c28", "PlayerRank_102": "5a9f3fb9a22b9d00456ade6f", "HeroRank_tracer_7": "5a9f3fc117d009006904b690", "PlayerPickRate_4627": "5aac79b9ee920a00452a348e", "CompositionUsage_ddssst_maptypes_control": "5a9d30e19f54541bcd381c69", "HeroRank_roadhog_30": "5a9f3fbc17d009006904b558", "PlayerRank_77": "5a9f3fb9a22b9d00456ade54", "Match_10242": "5a95aafcfe88c20038b3e9a4", "Match_10324": "5a95aafdfe88c20038b3ea07", "Match_10310": "5a95aafdfe88c20038b3e9f2", "Match_10564": "5a95aafcfe88c20038b3e9c2", "CompositionUsage_ddddtt_maptypes_assault": "5ab8c276ac502e57c9596d7f", "CompositionUsage_dddttt_maptypes_assault": "5ab8c276ac502e57c9596d80", "CompositionUsage_dstttt_maptypes_hybrid": "5ab8c277ac502e57c9596d81", "CompositionUsage_ddddtt_maps_volskaya_industries": "5ab8c277ac502e57c9596d82", "CompositionUsage_dddttt_maps_volskaya_industries": "5ab8c277ac502e57c9596d83", "CompositionUsage_dddstt_maps_nepal": "5ab8c277ac502e57c9596d84", "CompositionUsage_dstttt_maps_king's_row": "5ab8c277ac502e57c9596d85", "CompositionUsage_ddddtt_maps_route_66": "5ab8c277ac502e57c9596d86", "PlayerRank_105": "5ab8c8792f301e1c2c49fa8c", "PlayerRank_106": "5ab8c8792f301e1c2c49fa8d", "PlayerRank_107": "5ab8c8792f301e1c2c49fa8e", "PlayerRank_108": "5ab8c8792f301e1c2c49fa8f", "HeroRank_soldier-76_38": "5ab8c87c4773f70075c434f1", "HeroRank_widowmaker_31": "5ab8c87c4773f70075c434f3", "HeroRank_sombra_25": "5ab8c87c4773f70075c434f7", "HeroRank_hanzo_11": "5ab8c87d4773f70075c434f8", "HeroRank_mercy_30": "5ab8c87e4773f70075c43502", "HeroRank_mercy_29": "5ab8c87e4773f70075c43508", "HeroRank_widowmaker_32": "5ab8c87f4773f70075c4350d", "HeroRank_junkrat_24": "5ab8c87f4773f70075c43511", "HeroRank_ana_29": "5ab8c8804773f70075c43513", "HeroRank_lucio_24": "5ab8c8804773f70075c43514", "HeroRank_tracer_34": "5ab8c8814773f70075c43519", "HeroRank_zarya_29": "5ab8c8824773f70075c4351d", "HeroRank_mccree_28": "5ab8c8824773f70075c4351e", "HeroRank_reaper_15": "5ab8c8824773f70075c4351f", "HeroRank_soldier-76_37": "5ab8c8824773f70075c43520", "HeroRank_roadhog_43": "5ab8c8834773f70075c43525", "HeroRank_zarya_28": "5ab8c8834773f70075c43526", "HeroRank_mccree_27": "5ab8c8834773f70075c43527", "HeroRank_genji_28": "5ab8c8834773f70075c4352b", "HeroRank_genji_29": "5ab8c8844773f70075c43534", "HeroRank_widowmaker_30": "5ab8c8844773f70075c43535", "HeroRank_reinhardt_17": "5ab8c8844773f70075c43536", "HeroRank_doomfist_6": "5ab8c8844773f70075c43537", "HeroRank_mccree_29": "5ab8c8844773f70075c43538", "HeroRank_tracer_33": "5ab8c8844773f70075c43539", "HeroRank_roadhog_42": "5ab8c8844773f70075c4353c", "HeroRank_tracer_35": "5ab8c8854773f70075c4353e", "HeroRank_zarya_30": "5ab8c8854773f70075c4353f", "HeroRank_reinhardt_16": "5ab8c8854773f70075c43543", "HeroRank_mccree_30": "5ab8c8854773f70075c43545", "HeroRank_dva_24": "5ab8c8854773f70075c43546", "HeroRank_winston_21": "5ab8c8854773f70075c43548", "HeroRank_reinhardt_18": "5ab8c8854773f70075c4354b", "HeroRank_winston_20": "5ab8c8854773f70075c4354c", "HeroRank_dva_25": "5ab8c8854773f70075c4354d", "PlayerPickRate_5716": "5ab8c88844d90418a2381cf9", "PlayerPickRate_4139": "5ab8c88844d90418a2381cfa", "PlayerPickRate_5197": "5ab8c88844d90418a2381cfb", "PlayerPickRate_5207": "5ab8c88844d90418a2381cfc", "StageRank_preseason_5": "5ab8de47a22b9d0045fc6adf", "StageRank_league_1": "5ab8de47a22b9d0045fc6ae0", "StageRank_stage1_1": "5ab8de47a22b9d0045fc6ae1", "StageRank_stage2_1": "5ab8de47a22b9d0045fc6ae2", "StageRank_stage3_1": "5ab8de48a22b9d0045fc6b28", "StageRank_stage4_1": "5ab8de48a22b9d0045fc6b29", "StageRank_preseason_4": "5ab8de47a22b9d0045fc6ae5", "StageRank_league_2": "5ab8de47a22b9d0045fc6ae6", "StageRank_stage1_3": "5ab8de47a22b9d0045fc6ae7", "StageRank_stage2_2": "5ab8de47a22b9d0045fc6ae8", "StageRank_preseason_1": "5ab8de47a22b9d0045fc6aeb", "StageRank_league_3": "5ab8de47a22b9d0045fc6aec", "StageRank_stage1_5": "5ab8de47a22b9d0045fc6aed", "StageRank_stage2_4": "5ab8de47a22b9d0045fc6aef", "StageRank_league_4": "5ab8de47a22b9d0045fc6af2", "StageRank_stage1_7": "5ab8de47a22b9d0045fc6af3", "StageRank_stage2_3": "5ab8de47a22b9d0045fc6af4", "StageRank_preseason_9": "5ab8de47a22b9d0045fc6af7", "StageRank_league_5": "5ab8de47a22b9d0045fc6af8", "StageRank_stage1_2": "5ab8de47a22b9d0045fc6af9", "StageRank_stage2_7": "5ab8de47a22b9d0045fc6afa", "StageRank_preseason_6": "5ab8de47a22b9d0045fc6b0a", "StageRank_league_6": "5ab8de47a22b9d0045fc6afe", "StageRank_stage1_6": "5ab8de47a22b9d0045fc6aff", "StageRank_stage2_6": "5ab8de47a22b9d0045fc6b00", "StageRank_preseason_2": "5ab8de47a22b9d0045fc6b16", "StageRank_league_7": "5ab8de47a22b9d0045fc6b04", "StageRank_stage1_4": "5ab8de47a22b9d0045fc6b05", "StageRank_stage2_8": "5ab8de47a22b9d0045fc6b06", "StageRank_league_8": "5ab8de47a22b9d0045fc6b0b", "StageRank_stage1_8": "5ab8de47a22b9d0045fc6b0c", "StageRank_stage2_5": "5ab8de47a22b9d0045fc6b0d", "StageRank_preseason_8": "5ab8de47a22b9d0045fc6b10", "StageRank_league_9": "5ab8de47a22b9d0045fc6b11", "StageRank_stage1_9": "5ab8de47a22b9d0045fc6b12", "StageRank_stage2_9": "5ab8de47a22b9d0045fc6b13", "StageRank_league_10": "5ab8de47a22b9d0045fc6b17", "StageRank_stage1_10": "5ab8de47a22b9d0045fc6b18", "StageRank_stage2_11": "5ab8de47a22b9d0045fc6b19", "StageRank_preseason_10": "5ab8de47a22b9d0045fc6b1d", "StageRank_league_11": "5ab8de47a22b9d0045fc6b1e", "StageRank_stage1_11": "5ab8de47a22b9d0045fc6b1f", "StageRank_stage2_10": "5ab8de47a22b9d0045fc6b20", "StageRank_preseason_11": "5ab8de48a22b9d0045fc6b23", "StageRank_league_12": "5ab8de48a22b9d0045fc6b24", "StageRank_stage1_12": "5ab8de48a22b9d0045fc6b25", "StageRank_stage2_12": "5ab8de48a22b9d0045fc6b26"}